{
  "annotations": {
    "list": [
      {
        "builtIn": 1,
        "datasource": "-- Grafana --",
        "enable": false,
        "hide": true,
        "iconColor": "rgba(0, 211, 255, 1)",
        "name": "Annotations & Alerts",
        "type": "dashboard"
      }
    ]
  },
  "editable": true,
  "gnetId": null,
  "graphTooltip": 1,
  "iteration": 1584541181401,
  "links": [
    {
      "icon": "external link",
      "includeVars": false,
      "tags": [],
      "targetBlank": true,
      "title": "Sandbox Instances",
      "type": "link",
      "url": "https://console.cloud.google.com/kubernetes/workload?project=mlab-sandbox&organizationId=433637338589&workload_list_tablesize=50&workload_list_tablequery=%255B%257B_22k_22_3A_22is_system_22_2C_22t_22_3A10_2C_22v_22_3A_22_5C_22false_5C_22_22_2C_22s_22_3Atrue%257D_2C%257B_22k_22_3A_22metadata%252Fname_22_2C_22t_22_3A10_2C_22v_22_3A_22_5C_22gardener_5C_22_22%257D%255D"
    },
    {
      "icon": "external link",
      "tags": [],
      "targetBlank": true,
      "title": "Staging instances",
      "type": "link",
      "url": "https://pantheon.corp.google.com/kubernetes/workload?project=mlab-staging&organizationId=433637338589&workload_list_tablesize=50&workload_list_tablequery=%255B%257B_22k_22_3A_22is_system_22_2C_22t_22_3A10_2C_22v_22_3A_22_5C_22false_5C_22_22_2C_22s_22_3Atrue%257D_2C%257B_22k_22_3A_22metadata%252Fname_22_2C_22t_22_3A10_2C_22v_22_3A_22_5C_22gardener_5C_22_22%257D%255D"
    },
    {
      "icon": "external link",
      "tags": [],
      "targetBlank": true,
      "title": "Production Instances",
      "type": "link",
      "url": "https://console.cloud.google.com/kubernetes/workload?project=mlab-oti&organizationId=433637338589&workload_list_tablesize=50&workload_list_tablequery=%255B%257B_22k_22_3A_22is_system_22_2C_22t_22_3A10_2C_22v_22_3A_22_5C_22false_5C_22_22_2C_22s_22_3Atrue%257D_2C%257B_22k_22_3A_22metadata%252Fname_22_2C_22t_22_3A10_2C_22v_22_3A_22_5C_22gardener_5C_22_22%257D%255D"
    }
  ],
  "panels": [
    {
      "aliasColors": {},
      "bars": true,
      "dashLength": 10,
      "dashes": false,
      "datasource": "$prometheusDatasource",
      "fill": 1,
      "fillGradient": 0,
      "gridPos": {
        "h": 6,
        "w": 6,
        "x": 0,
        "y": 0
      },
      "id": 19,
      "legend": {
        "avg": false,
        "current": false,
        "max": false,
        "min": false,
        "show": false,
        "total": false,
        "values": false
      },
      "lines": false,
      "linewidth": 1,
      "links": [],
      "nullPointMode": "null",
      "options": {
        "dataLinks": []
      },
      "percentage": false,
      "pointradius": 5,
      "points": false,
      "renderer": "flot",
      "seriesOverrides": [],
      "spaceLength": 10,
      "stack": false,
      "steppedLine": false,
      "targets": [
        {
          "expr": "bq_gardener_parse_time_age_days",
          "format": "time_series",
          "instant": true,
          "interval": "",
          "intervalFactor": 1,
          "legendFormat": "{{datatype}}",
          "refId": "A"
        }
      ],
      "thresholds": [],
      "timeFrom": null,
      "timeRegions": [],
      "timeShift": null,
      "title": "Reprocessing Period",
      "tooltip": {
        "shared": false,
        "sort": 0,
        "value_type": "individual"
      },
      "type": "graph",
      "xaxis": {
        "buckets": null,
        "mode": "series",
        "name": null,
        "show": true,
        "values": [
          "total"
        ]
      },
      "yaxes": [
        {
          "decimals": 1,
          "format": "none",
          "label": "Days",
          "logBase": 1,
          "max": null,
          "min": "0",
          "show": true
        },
        {
          "decimals": 0,
          "format": "short",
          "label": "",
          "logBase": 1,
          "max": null,
          "min": null,
          "show": true
        }
      ],
      "yaxis": {
        "align": false,
        "alignLevel": null
      }
    },
    {
      "aliasColors": {},
      "bars": false,
      "dashLength": 10,
      "dashes": false,
      "datasource": "$pipelineDatasource",
      "fill": 1,
      "fillGradient": 0,
      "gridPos": {
        "h": 6,
        "w": 6,
        "x": 6,
        "y": 0
      },
      "id": 2,
      "legend": {
        "avg": false,
        "current": false,
        "max": false,
        "min": false,
        "show": false,
        "total": false,
        "values": false
      },
      "lines": true,
      "linewidth": 1,
      "links": [],
      "nullPointMode": "null",
      "options": {
        "dataLinks": []
      },
      "percentage": false,
      "pointradius": 5,
      "points": false,
      "renderer": "flot",
      "seriesOverrides": [
        {
          "alias": "/Warning:/",
          "color": "#e5ac0e"
        },
        {
          "alias": "/Failure:/",
          "color": "#bf1b00"
        }
      ],
      "spaceLength": 10,
      "stack": false,
      "steppedLine": false,
      "targets": [
        {
          "expr": "irate(gardener_warning_total{container=\"etl-gardener\"}[12h])",
          "format": "time_series",
          "hide": true,
          "intervalFactor": 1,
          "legendFormat": "{{status}}",
          "refId": "A"
        },
        {
          "expr": "irate(gardener_fail_total{container=\"etl-gardener\"}[12h])",
          "format": "time_series",
          "hide": true,
          "interval": "",
          "intervalFactor": 1,
          "legendFormat": "{{status}}",
          "refId": "B"
        },
        {
          "expr": "3600 * rate(gardener_warning_total{container=\"etl-gardener\", deployment=~\"$deployment\"}[1h])",
          "format": "time_series",
          "intervalFactor": 1,
          "legendFormat": "Warning: {{status}}",
          "refId": "C"
        },
        {
          "expr": "3600 * rate(gardener_fail_total{container=\"etl-gardener\", deployment=~\"$deployment\"}[1h])",
          "format": "time_series",
          "intervalFactor": 1,
          "legendFormat": "Failure: {{status}}",
          "refId": "D"
        }
      ],
      "thresholds": [],
      "timeFrom": null,
      "timeRegions": [],
      "timeShift": null,
      "title": "Hourly Warning and Failure Rates",
      "tooltip": {
        "shared": true,
        "sort": 0,
        "value_type": "individual"
      },
      "type": "graph",
      "xaxis": {
        "buckets": null,
        "mode": "time",
        "name": null,
        "show": true,
        "values": []
      },
      "yaxes": [
        {
          "decimals": null,
          "format": "short",
          "label": "",
          "logBase": 1,
          "max": null,
          "min": "0",
          "show": true
        },
        {
          "format": "short",
          "label": null,
          "logBase": 1,
          "max": null,
          "min": null,
          "show": true
        }
      ],
      "yaxis": {
        "align": false,
        "alignLevel": null
      }
    },
    {
      "aliasColors": {},
      "bars": false,
      "dashLength": 10,
      "dashes": false,
      "datasource": "$pipelineDatasource",
      "fill": 1,
      "fillGradient": 0,
      "gridPos": {
        "h": 6,
        "w": 4,
        "x": 12,
        "y": 0
      },
      "id": 4,
      "legend": {
        "avg": false,
        "current": false,
        "max": false,
        "min": false,
        "show": false,
        "total": false,
        "values": false
      },
      "lines": true,
      "linewidth": 1,
      "links": [],
      "nullPointMode": "null",
      "options": {
        "dataLinks": []
      },
      "percentage": false,
      "pointradius": 5,
      "points": false,
      "renderer": "flot",
      "seriesOverrides": [],
      "spaceLength": 10,
      "stack": false,
      "steppedLine": false,
      "targets": [
        {
          "expr": "rate(process_cpu_seconds_total{container=\"etl-gardener\", deployment=~\"$deployment\"}[5m])",
          "format": "time_series",
          "intervalFactor": 1,
          "legendFormat": "{{deployment}}",
          "refId": "A"
        }
      ],
      "thresholds": [],
      "timeFrom": null,
      "timeRegions": [],
      "timeShift": null,
      "title": "CPU Utilization",
      "tooltip": {
        "shared": true,
        "sort": 0,
        "value_type": "individual"
      },
      "type": "graph",
      "xaxis": {
        "buckets": null,
        "mode": "time",
        "name": null,
        "show": true,
        "values": []
      },
      "yaxes": [
        {
          "format": "percentunit",
          "label": null,
          "logBase": 1,
          "max": null,
          "min": null,
          "show": true
        },
        {
          "format": "short",
          "label": null,
          "logBase": 1,
          "max": null,
          "min": null,
          "show": true
        }
      ],
      "yaxis": {
        "align": false,
        "alignLevel": null
      }
    },
    {
      "aliasColors": {},
      "bars": false,
      "dashLength": 10,
      "dashes": false,
      "datasource": "$pipelineDatasource",
      "fill": 1,
      "fillGradient": 0,
      "gridPos": {
        "h": 6,
        "w": 4,
        "x": 16,
        "y": 0
      },
      "id": 12,
      "legend": {
        "avg": false,
        "current": false,
        "max": false,
        "min": false,
        "show": false,
        "total": false,
        "values": false
      },
      "lines": true,
      "linewidth": 1,
      "links": [],
      "nullPointMode": "null",
      "options": {
        "dataLinks": []
      },
      "percentage": false,
      "pointradius": 5,
      "points": false,
      "renderer": "flot",
      "seriesOverrides": [],
      "spaceLength": 10,
      "stack": false,
      "steppedLine": false,
      "targets": [
        {
          "expr": "go_goroutines{container=\"etl-gardener\", deployment=~\"$deployment\"}",
          "format": "time_series",
          "intervalFactor": 1,
          "legendFormat": "{{deployment}}",
          "refId": "A"
        },
        {
          "expr": "",
          "format": "time_series",
          "intervalFactor": 1,
          "legendFormat": "",
          "refId": "B"
        }
      ],
      "thresholds": [],
      "timeFrom": null,
      "timeRegions": [],
      "timeShift": null,
      "title": "GoRoutine Count",
      "tooltip": {
        "shared": true,
        "sort": 0,
        "value_type": "individual"
      },
      "type": "graph",
      "xaxis": {
        "buckets": null,
        "mode": "time",
        "name": null,
        "show": true,
        "values": []
      },
      "yaxes": [
        {
          "format": "short",
          "label": null,
          "logBase": 1,
          "max": null,
          "min": "0",
          "show": true
        },
        {
          "format": "short",
          "label": null,
          "logBase": 1,
          "max": null,
          "min": null,
          "show": true
        }
      ],
      "yaxis": {
        "align": false,
        "alignLevel": null
      }
    },
    {
      "aliasColors": {},
      "bars": false,
      "dashLength": 10,
      "dashes": false,
      "datasource": "$pipelineDatasource",
      "fill": 1,
      "fillGradient": 0,
      "gridPos": {
        "h": 6,
        "w": 4,
        "x": 20,
        "y": 0
      },
      "id": 5,
      "legend": {
        "avg": false,
        "current": false,
        "max": false,
        "min": false,
        "show": false,
        "total": false,
        "values": false
      },
      "lines": true,
      "linewidth": 1,
      "links": [],
      "nullPointMode": "null",
      "options": {
        "dataLinks": []
      },
      "percentage": false,
      "pointradius": 5,
      "points": false,
      "renderer": "flot",
      "seriesOverrides": [],
      "spaceLength": 10,
      "stack": false,
      "steppedLine": false,
      "targets": [
        {
          "expr": "process_virtual_memory_bytes{container=\"etl-gardener\", deployment=~\"$deployment\"}",
          "format": "time_series",
          "intervalFactor": 1,
          "legendFormat": "{{deployment}}",
          "refId": "A"
        }
      ],
      "thresholds": [],
      "timeFrom": null,
      "timeRegions": [],
      "timeShift": null,
      "title": "Virtual Memory",
      "tooltip": {
        "shared": true,
        "sort": 0,
        "value_type": "individual"
      },
      "type": "graph",
      "xaxis": {
        "buckets": null,
        "mode": "time",
        "name": null,
        "show": true,
        "values": []
      },
      "yaxes": [
        {
          "decimals": 0,
          "format": "decbytes",
          "label": null,
          "logBase": 1,
          "max": null,
          "min": "0",
          "show": true
        },
        {
          "format": "short",
          "label": null,
          "logBase": 1,
          "max": null,
          "min": null,
          "show": true
        }
      ],
      "yaxis": {
        "align": false,
        "alignLevel": null
      }
    },
    {
      "aliasColors": {},
      "bars": false,
      "dashLength": 10,
      "dashes": false,
      "datasource": "$pipelineDatasource",
      "fill": 1,
      "fillGradient": 0,
      "gridPos": {
        "h": 6,
        "w": 12,
        "x": 0,
        "y": 6
      },
      "id": 7,
      "legend": {
        "avg": false,
        "current": false,
        "max": false,
        "min": false,
        "show": false,
        "total": false,
        "values": false
      },
      "lines": true,
      "linewidth": 1,
      "links": [],
      "nullPointMode": "null",
      "options": {
        "dataLinks": []
      },
      "percentage": false,
      "pointradius": 5,
      "points": false,
      "renderer": "flot",
      "seriesOverrides": [],
      "spaceLength": 10,
      "stack": false,
      "steppedLine": false,
      "targets": [
        {
          "expr": "gardener_tasks_in_flight{deployment=~\"$deployment\", deployment!~\".*universal\"}",
          "format": "time_series",
          "hide": false,
          "intervalFactor": 1,
          "legendFormat": "{{deployment}}",
          "refId": "A"
        },
        {
          "expr": "gardener_tasks_in_flight{deployment=~\".*universal\"}",
          "format": "time_series",
          "intervalFactor": 1,
          "legendFormat": "{{datatype}}",
          "refId": "B"
        }
      ],
      "thresholds": [],
      "timeFrom": null,
      "timeRegions": [],
      "timeShift": null,
      "title": "Tasks In Flight",
      "tooltip": {
        "shared": true,
        "sort": 0,
        "value_type": "individual"
      },
      "type": "graph",
      "xaxis": {
        "buckets": null,
        "mode": "time",
        "name": null,
        "show": true,
        "values": []
      },
      "yaxes": [
        {
          "format": "short",
          "label": null,
          "logBase": 1,
          "max": null,
          "min": "0",
          "show": true
        },
        {
          "format": "short",
          "label": null,
          "logBase": 1,
          "max": null,
          "min": null,
          "show": true
        }
      ],
      "yaxis": {
        "align": false,
        "alignLevel": null
      }
    },
    {
      "aliasColors": {},
      "bars": false,
      "dashLength": 10,
      "dashes": false,
      "datasource": "$pipelineDatasource",
      "description": "How long each date spends in each processing state.\nIf Processing exceeds 12 hours, then there will likely be data loss from expiration in the task queue.",
      "fill": 0,
      "fillGradient": 0,
      "gridPos": {
        "h": 12,
        "w": 12,
        "x": 12,
        "y": 6
      },
      "id": 10,
      "legend": {
        "avg": false,
        "current": false,
        "max": false,
        "min": false,
        "show": false,
        "total": false,
        "values": false
      },
      "lines": true,
      "linewidth": 1,
      "links": [],
      "nullPointMode": "connected",
      "options": {
        "dataLinks": []
      },
      "percentage": false,
      "pointradius": 0.5,
      "points": true,
      "renderer": "flot",
      "seriesOverrides": [],
      "spaceLength": 10,
      "stack": false,
      "steppedLine": false,
      "targets": [
        {
          "expr": "histogram_quantile(0.5, sum(rate(gardener_state_time_histogram_bucket{deployment=~\"$deployment\", deployment!~\".*universal\"}[1h])) by (deployment, state, le))",
          "format": "time_series",
          "hide": true,
          "interval": "",
          "intervalFactor": 1,
          "legendFormat": "{{state}} {{deployment}}",
          "refId": "B"
        },
        {
          "expr": "histogram_quantile(0.95, sum(rate(gardener_state_time_histogram_bucket{deployment=~\"$deployment\", deployment!~\".*universal\"}[1h])) by (deployment, state, le))",
          "format": "time_series",
          "hide": false,
          "interval": "",
          "intervalFactor": 1,
          "legendFormat": "{{state}} {{deployment}}",
          "refId": "C"
        },
        {
          "expr": "histogram_quantile(0.5, sum(rate(gardener_state_time_histogram_bucket{deployment=~\".*universal\"}[1h])) by (deployment, state, datatype, le))",
          "format": "time_series",
          "hide": true,
          "interval": "",
          "intervalFactor": 1,
          "legendFormat": "{{state}} {{datatype}}",
          "refId": "A"
        },
        {
          "expr": "histogram_quantile(0.95, sum(rate(gardener_state_time_histogram_bucket{deployment=~\".*universal\"}[1h])) by (deployment, state, datatype, le))",
          "format": "time_series",
          "hide": false,
          "interval": "",
          "intervalFactor": 1,
          "legendFormat": "{{state}} {{datatype}}",
          "refId": "D"
        }
      ],
      "thresholds": [
        {
          "colorMode": "critical",
          "fill": true,
          "line": true,
          "op": "gt",
          "value": 43200,
          "yaxis": "left"
        }
      ],
      "timeFrom": null,
      "timeRegions": [],
      "timeShift": null,
      "title": "Time in State (95th Percentile)",
      "tooltip": {
        "shared": true,
        "sort": 2,
        "value_type": "individual"
      },
      "type": "graph",
      "xaxis": {
        "buckets": null,
        "mode": "time",
        "name": null,
        "show": true,
        "values": []
      },
      "yaxes": [
        {
          "decimals": null,
          "format": "s",
          "label": null,
          "logBase": 10,
          "max": "50000",
          "min": "0.1",
          "show": true
        },
        {
          "format": "short",
          "label": null,
          "logBase": 1,
          "max": null,
          "min": null,
          "show": true
        }
      ],
      "yaxis": {
        "align": false,
        "alignLevel": null
      }
    },
    {
      "aliasColors": {},
      "bars": false,
      "dashLength": 10,
      "dashes": false,
      "datasource": "$pipelineDatasource",
      "description": "Number of tasks started and completed, per hour.",
      "fill": 1,
      "fillGradient": 0,
      "gridPos": {
        "h": 6,
        "w": 12,
        "x": 0,
        "y": 12
      },
      "id": 9,
      "legend": {
        "avg": false,
        "current": false,
        "max": false,
        "min": false,
        "show": false,
        "total": false,
        "values": false
      },
      "lines": true,
      "linewidth": 1,
      "links": [],
      "nullPointMode": "null",
      "options": {
        "dataLinks": []
      },
      "percentage": false,
      "pointradius": 5,
      "points": false,
      "renderer": "flot",
      "seriesOverrides": [
        {
          "alias": "Completed etl-gardener-disco",
          "color": "#508642"
        },
        {
          "alias": "Completed etl-gardener-ndt",
          "color": "#cca300"
        },
        {
          "alias": "Completed etl-gardener-sidestream",
          "color": "#e24d42"
        },
        {
          "alias": "Started etl-gardener-disco",
          "color": "#508642"
        },
        {
          "alias": "Started etl-gardener-ndt",
          "color": "#e5ac0e"
        },
        {
          "alias": "Started etl-gardener-sidestream",
          "color": "#e24d42"
        }
      ],
      "spaceLength": 10,
      "stack": false,
      "steppedLine": false,
      "targets": [
        {
          "expr": "sum by(deployment) (increase(gardener_started_total{deployment=~\"$deployment\", deployment!~\".*universal\"}[1h]))",
          "format": "time_series",
          "hide": false,
          "intervalFactor": 1,
          "legendFormat": "Started {{deployment}}",
          "refId": "A"
        },
        {
          "expr": "sum by(deployment) (-increase(gardener_completed_total{deployment=~\"$deployment\", deployment!~\".*universal\"}[1h]))",
          "format": "time_series",
          "hide": false,
          "intervalFactor": 1,
          "legendFormat": "Completed {{deployment}}",
          "refId": "B"
        },
        {
          "expr": "sum by(datatype) (increase(gardener_started_total{deployment=~\"$deployment\", deployment=~\".*universal\"}[1h]))",
          "format": "time_series",
          "hide": false,
          "intervalFactor": 1,
          "legendFormat": "Started {{datatype}}",
          "refId": "C"
        },
        {
          "expr": "sum by(datatype) (-increase(gardener_completed_total{deployment=~\"$deployment\", deployment=~\".*universal\"}[1h]))",
          "format": "time_series",
          "hide": false,
          "intervalFactor": 1,
          "legendFormat": "Completed {{datatype}}",
          "refId": "D"
        }
      ],
      "thresholds": [],
      "timeFrom": null,
      "timeRegions": [],
      "timeShift": null,
      "title": "Start and Completion Rate (hourly)",
      "tooltip": {
        "shared": true,
        "sort": 2,
        "value_type": "individual"
      },
      "type": "graph",
      "xaxis": {
        "buckets": null,
        "mode": "time",
        "name": null,
        "show": true,
        "values": []
      },
      "yaxes": [
        {
          "decimals": null,
          "format": "short",
          "label": "Tasks / Hour",
          "logBase": 1,
          "max": null,
          "min": null,
          "show": true
        },
        {
          "format": "short",
          "label": null,
          "logBase": 1,
          "max": null,
          "min": null,
          "show": true
        }
      ],
      "yaxis": {
        "align": false,
        "alignLevel": null
      }
    },
    {
      "aliasColors": {},
      "bars": false,
      "dashLength": 10,
      "dashes": false,
      "datasource": "$pipelineDatasource",
      "description": "",
      "fill": 1,
      "fillGradient": 0,
      "gridPos": {
        "h": 6,
        "w": 8,
        "x": 0,
        "y": 18
      },
      "id": 13,
      "legend": {
        "avg": false,
        "current": false,
        "max": false,
        "min": false,
        "show": false,
        "total": false,
        "values": false
      },
      "lines": true,
      "linewidth": 1,
      "links": [],
      "nullPointMode": "null",
      "options": {
        "dataLinks": []
      },
      "percentage": false,
      "pointradius": 5,
      "points": false,
      "renderer": "flot",
      "seriesOverrides": [
        {
          "alias": "Completed etl-gardener-disco",
          "color": "#508642"
        },
        {
          "alias": "Completed etl-gardener-ndt",
          "color": "#cca300"
        },
        {
          "alias": "Completed etl-gardener-sidestream",
          "color": "#e24d42"
        },
        {
          "alias": "Started etl-gardener-disco",
          "color": "#508642"
        },
        {
          "alias": "Started etl-gardener-ndt",
          "color": "#e5ac0e"
        },
        {
          "alias": "Started etl-gardener-sidestream",
          "color": "#e24d42"
        }
      ],
      "spaceLength": 10,
      "stack": false,
      "steppedLine": false,
      "targets": [
        {
          "expr": "sum by(deployment) (4*increase(gardener_completed_total{deployment=~\"$deployment\", deployment!~\".*universal\"}[6h]))",
          "format": "time_series",
          "hide": false,
          "intervalFactor": 1,
          "legendFormat": "Completed {{deployment}}",
          "refId": "B"
        },
        {
          "expr": "sum by(deployment, datatype) (4*increase(gardener_completed_total{deployment=~\"$deployment\", deployment=~\".*universal\"}[6h]))",
          "format": "time_series",
          "hide": false,
          "intervalFactor": 1,
          "legendFormat": "Completed {{datatype}}",
          "refId": "A"
        }
      ],
      "thresholds": [
        {
          "colorMode": "critical",
          "fill": true,
          "line": true,
          "op": "lt",
          "value": 40,
          "yaxis": "left"
        }
      ],
      "timeFrom": null,
      "timeRegions": [],
      "timeShift": null,
      "title": "SLO: Completion Rate (Tasks / day)",
      "tooltip": {
        "shared": true,
        "sort": 2,
        "value_type": "individual"
      },
      "type": "graph",
      "xaxis": {
        "buckets": null,
        "mode": "time",
        "name": null,
        "show": true,
        "values": []
      },
      "yaxes": [
        {
          "decimals": null,
          "format": "short",
          "label": "Tasks / Day",
          "logBase": 1,
          "max": null,
          "min": "0",
          "show": true
        },
        {
          "format": "short",
          "label": null,
          "logBase": 1,
          "max": null,
          "min": null,
          "show": true
        }
      ],
      "yaxis": {
        "align": false,
        "alignLevel": null
      }
    },
    {
      "aliasColors": {},
      "bars": false,
      "dashLength": 10,
      "dashes": false,
      "datasource": "$pipelineDatasource",
      "description": "",
      "fill": 0,
      "fillGradient": 0,
      "gridPos": {
        "h": 6,
        "w": 8,
        "x": 8,
        "y": 18
      },
      "id": 21,
      "legend": {
        "avg": false,
        "current": false,
        "max": false,
        "min": false,
        "rightSide": false,
        "show": false,
        "total": false,
        "values": false
      },
      "lines": true,
      "linewidth": 1,
      "links": [],
      "nullPointMode": "null",
      "options": {
        "dataLinks": []
      },
      "percentage": false,
      "pointradius": 5,
      "points": false,
      "renderer": "flot",
      "seriesOverrides": [
        {
          "alias": "/Avg Bytes.*/",
          "yaxis": 2
        }
      ],
      "spaceLength": 10,
      "stack": false,
      "steppedLine": false,
      "targets": [
        {
          "expr": "histogram_quantile(0.99, avg(gardener_empty_stats_recovery_sec) by (version, status, le))",
          "format": "time_series",
          "hide": false,
          "interval": "",
          "intervalFactor": 1,
          "legendFormat": "{{status}} {{version}}",
          "refId": "B"
        }
      ],
      "thresholds": [],
      "timeFrom": null,
      "timeRegions": [],
      "timeShift": null,
      "title": "Empty TQ Stats Resolution Time",
      "tooltip": {
        "shared": true,
        "sort": 2,
        "value_type": "individual"
      },
      "type": "graph",
      "xaxis": {
        "buckets": null,
        "mode": "time",
        "name": null,
        "show": true,
        "values": []
      },
      "yaxes": [
        {
          "decimals": null,
          "format": "decbytes",
          "label": "Bytes / File",
          "logBase": 10,
          "max": null,
          "min": null,
          "show": true
        },
        {
          "format": "decbytes",
          "label": "Bytes / File",
          "logBase": 10,
          "max": null,
          "min": null,
          "show": false
        }
      ],
      "yaxis": {
        "align": false,
        "alignLevel": null
      }
    },
    {
      "aliasColors": {},
      "bars": false,
      "dashLength": 10,
      "dashes": false,
      "datasource": "$pipelineDatasource",
      "description": "Task dates of the most recent updates to each task state.\n\nNOTE: In sandbox, we now process only a small subset of the requests, to get high throughput and test across the full date range quickly.  Cycle time is less than a day for sandbox, compared with one or two weeks for production.",
      "fill": 0,
      "fillGradient": 0,
      "gridPos": {
        "h": 6,
        "w": 8,
        "x": 16,
        "y": 18
      },
      "id": 15,
      "legend": {
        "avg": false,
        "current": false,
        "max": false,
        "min": false,
        "show": false,
        "total": false,
        "values": false
      },
      "lines": true,
      "linewidth": 1,
      "links": [],
      "nullPointMode": "null",
      "options": {
        "dataLinks": []
      },
      "percentage": false,
      "pointradius": 5,
      "points": false,
      "renderer": "flot",
      "seriesOverrides": [],
      "spaceLength": 10,
      "stack": false,
      "steppedLine": false,
      "targets": [
        {
          "expr": "1000*quantile_over_time(0.2, gardener_state_date{deployment=~\"$deployment\", deployment!=\"etl-gardener-universal\"}[20m])",
          "format": "time_series",
          "hide": false,
          "intervalFactor": 1,
          "legendFormat": "{{deployment}} {{state}}",
          "refId": "A"
        },
        {
          "expr": "1000*quantile_over_time(0.7, gardener_state_date{deployment=~\"$deployment\"}[10m])",
          "format": "time_series",
          "hide": true,
          "intervalFactor": 1,
          "legendFormat": "{{deployment}} {{type}} {{state}}",
          "refId": "B"
        },
        {
          "expr": "1000*quantile_over_time(0.2, gardener_state_date{deployment=\"etl-gardener-universal\", datatype!=\"\"}[20m])",
          "format": "time_series",
          "hide": false,
          "intervalFactor": 1,
          "legendFormat": "{{datatype}} {{state}}",
          "refId": "C"
        }
      ],
      "thresholds": [],
      "timeFrom": null,
      "timeRegions": [],
      "timeShift": null,
      "title": "Task Date of Recent State Updates",
      "tooltip": {
        "shared": true,
        "sort": 2,
        "value_type": "individual"
      },
      "type": "graph",
      "xaxis": {
        "buckets": null,
        "mode": "time",
        "name": null,
        "show": true,
        "values": []
      },
      "yaxes": [
        {
          "decimals": null,
          "format": "dateTimeAsIso",
          "label": "State update for task date",
          "logBase": 1,
          "max": null,
          "min": null,
          "show": true
        },
        {
          "format": "short",
          "label": null,
          "logBase": 1,
          "max": null,
          "min": null,
          "show": true
        }
      ],
      "yaxis": {
        "align": false,
        "alignLevel": null
      }
    },
    {
      "aliasColors": {},
      "bars": false,
      "dashLength": 10,
      "dashes": false,
      "datasource": "$pipelineDatasource",
      "description": "This measures the bytes submitted for processing. \n It reflects the ETL throughput, which is governed by the task queue rate and concurrency settings.\n\nThe rate is governed by how fast the ETL pipeline drains the task queues.  The balance across types is governed by the rate/concurrency settings on the queues.\n\nThis is fundamentally rather lumpy at the 10 minute level, so we average over an hour or more.  Aside from the fine-grained lumpiness, this should be the most stable of the throughput metrics, because it reflects the quantity of data, rather than the number or size of files.",
      "fill": 0,
      "fillGradient": 0,
      "gridPos": {
        "h": 6,
        "w": 8,
        "x": 0,
        "y": 24
      },
      "id": 16,
      "legend": {
        "avg": false,
        "current": false,
        "max": false,
        "min": false,
        "show": false,
        "total": false,
        "values": false
      },
      "lines": true,
      "linewidth": 1,
      "links": [],
      "nullPointMode": "null",
      "options": {
        "dataLinks": []
      },
      "percentage": false,
      "pointradius": 5,
      "points": false,
      "renderer": "flot",
      "seriesOverrides": [],
      "spaceLength": 10,
      "stack": false,
      "steppedLine": false,
      "targets": [
        {
          "expr": "sum by(deployment, year)(rate(gardener_bytes_sum{deployment=~\"$deployment\"}[1h])*3600)",
          "format": "time_series",
          "hide": false,
          "intervalFactor": 1,
          "legendFormat": "{{deployment}} {{year}}",
          "refId": "A"
        }
      ],
      "thresholds": [],
      "timeFrom": null,
      "timeRegions": [],
      "timeShift": null,
      "title": "Byte Rate",
      "tooltip": {
        "shared": true,
        "sort": 2,
        "value_type": "individual"
      },
      "type": "graph",
      "xaxis": {
        "buckets": null,
        "mode": "time",
        "name": null,
        "show": true,
        "values": []
      },
      "yaxes": [
        {
          "decimals": null,
          "format": "decbytes",
          "label": "Bytes/Hour",
          "logBase": 10,
          "max": null,
          "min": null,
          "show": true
        },
        {
          "format": "short",
          "label": "",
          "logBase": 1,
          "max": null,
          "min": null,
          "show": true
        }
      ],
      "yaxis": {
        "align": false,
        "alignLevel": null
      }
    },
    {
      "aliasColors": {},
      "bars": false,
      "dashLength": 10,
      "dashes": false,
      "datasource": "$pipelineDatasource",
      "description": "",
      "fill": 0,
      "fillGradient": 0,
      "gridPos": {
        "h": 6,
        "w": 8,
        "x": 8,
        "y": 24
      },
      "id": 17,
      "legend": {
        "avg": false,
        "current": false,
        "max": false,
        "min": false,
        "rightSide": false,
        "show": false,
        "total": false,
        "values": false
      },
      "lines": true,
      "linewidth": 1,
      "links": [],
      "nullPointMode": "null",
      "options": {
        "dataLinks": []
      },
      "percentage": false,
      "pointradius": 5,
      "points": false,
      "renderer": "flot",
      "seriesOverrides": [
        {
          "alias": "/Avg Bytes.*/",
          "yaxis": 2
        }
      ],
      "spaceLength": 10,
      "stack": false,
      "steppedLine": false,
      "targets": [
        {
          "expr": "sum by(deployment, year)(rate(gardener_files_sum{deployment=~\"$deployment\"}[1h])*3600)",
          "format": "time_series",
          "hide": false,
          "interval": "",
          "intervalFactor": 1,
          "legendFormat": "{{deployment}} {{year}}",
          "refId": "A"
        }
      ],
      "thresholds": [],
      "timeFrom": null,
      "timeRegions": [],
      "timeShift": null,
      "title": "File Rate",
      "tooltip": {
        "shared": true,
        "sort": 2,
        "value_type": "individual"
      },
      "type": "graph",
      "xaxis": {
        "buckets": null,
        "mode": "time",
        "name": null,
        "show": true,
        "values": []
      },
      "yaxes": [
        {
          "decimals": null,
          "format": "short",
          "label": "Files / Hour",
          "logBase": 10,
          "max": null,
          "min": null,
          "show": true
        },
        {
          "format": "decbytes",
          "label": "Bytes / File",
          "logBase": 10,
          "max": null,
          "min": null,
          "show": false
        }
      ],
      "yaxis": {
        "align": false,
        "alignLevel": null
      }
    },
    {
      "aliasColors": {},
      "bars": false,
      "dashLength": 10,
      "dashes": false,
      "datasource": "$pipelineDatasource",
      "description": "",
      "fill": 0,
      "fillGradient": 0,
      "gridPos": {
        "h": 6,
        "w": 8,
        "x": 16,
        "y": 24
      },
      "id": 20,
      "legend": {
        "avg": false,
        "current": false,
        "max": false,
        "min": false,
        "rightSide": false,
        "show": false,
        "total": false,
        "values": false
      },
      "lines": true,
      "linewidth": 1,
      "links": [],
      "nullPointMode": "null",
      "options": {
        "dataLinks": []
      },
      "percentage": false,
      "pointradius": 5,
      "points": false,
      "renderer": "flot",
      "seriesOverrides": [
        {
          "alias": "/Avg Bytes.*/",
          "yaxis": 2
        }
      ],
      "spaceLength": 10,
      "stack": false,
      "steppedLine": false,
      "targets": [
        {
          "expr": "avg by(deployment, year) (\n    rate(gardener_bytes_sum{deployment=~\"$deployment\"}[1h]) /\n    rate(gardener_files_sum{deployment=~\"$deployment\"}[1h]))",
          "format": "time_series",
          "hide": false,
          "interval": "",
          "intervalFactor": 1,
          "legendFormat": "{{deployment}} {{year}}",
          "refId": "B"
        }
      ],
      "thresholds": [],
      "timeFrom": null,
      "timeRegions": [],
      "timeShift": null,
      "title": "Bytes / File",
      "tooltip": {
        "shared": true,
        "sort": 2,
        "value_type": "individual"
      },
      "type": "graph",
      "xaxis": {
        "buckets": null,
        "mode": "time",
        "name": null,
        "show": true,
        "values": []
      },
      "yaxes": [
        {
          "decimals": null,
          "format": "decbytes",
          "label": "Bytes / File",
          "logBase": 10,
          "max": null,
          "min": null,
          "show": true
        },
        {
          "format": "decbytes",
          "label": "Bytes / File",
          "logBase": 10,
          "max": null,
          "min": null,
          "show": false
        }
      ],
      "yaxis": {
        "align": false,
        "alignLevel": null
      }
    }
  ],
  "refresh": "5m",
  "schemaVersion": 20,
  "style": "dark",
  "tags": [],
  "templating": {
    "list": [
      {
        "allValue": null,
        "current": {
          "selected": false,
          "tags": [],
          "text": "mlab-oti",
          "value": "mlab-oti"
        },
        "hide": 0,
        "includeAll": false,
        "label": "Project",
        "multi": false,
        "name": "project",
        "options": [
          {
            "selected": false,
            "text": "mlab-sandbox",
            "value": "mlab-sandbox"
          },
          {
            "selected": false,
            "text": "mlab-staging",
            "value": "mlab-staging"
          },
          {
            "selected": true,
            "text": "mlab-oti",
            "value": "mlab-oti"
          }
        ],
        "query": "mlab-sandbox,mlab-staging,mlab-oti",
        "skipUrlSync": false,
        "type": "custom"
      },
      {
        "current": {
          "text": "Data Proc (mlab-oti)",
          "value": "Data Proc (mlab-oti)"
        },
        "hide": 0,
        "includeAll": false,
        "label": "Data Processing",
        "multi": false,
        "name": "pipelineDatasource",
        "options": [],
        "query": "prometheus",
        "refresh": 1,
        "regex": "/Data Proc.*$project/",
        "skipUrlSync": false,
        "type": "datasource"
      },
      {
        "current": {
          "text": "Prometheus (mlab-oti)",
          "value": "Prometheus (mlab-oti)"
        },
        "hide": 2,
        "includeAll": false,
        "label": "Prometheus",
        "multi": false,
        "name": "prometheusDatasource",
        "options": [],
        "query": "prometheus",
        "refresh": 1,
        "regex": "/Prometheus.*$project/",
        "skipUrlSync": false,
        "type": "datasource"
      },
      {
        "allValue": "etl-gardener-.*",
        "current": {
          "text": "All",
          "value": "$__all"
        },
        "datasource": "$pipelineDatasource",
        "definition": "label_values(up{deployment=~\"etl-gardener-.*\"}, deployment)",
        "hide": 0,
        "includeAll": true,
        "label": "Deployments",
        "multi": false,
        "name": "deployment",
        "options": [],
        "query": "label_values(up{deployment=~\"etl-gardener-.*\"}, deployment)",
        "refresh": 2,
        "regex": "",
        "skipUrlSync": false,
        "sort": 1,
        "tagValuesQuery": "",
        "tags": [],
        "tagsQuery": "",
        "type": "query",
        "useTags": false
      },
      {
        "allValue": ".*",
        "current": {
          "text": "All",
          "value": [
            "$__all"
          ]
        },
        "datasource": "$pipelineDatasource",
        "definition": "label_values(gardener_tasks_in_flight{deployment=~\"$deployment\"}, datatype)",
        "hide": 0,
        "includeAll": true,
        "label": "Datatypes",
        "multi": true,
        "name": "datatypes",
        "options": [],
        "query": "label_values(gardener_tasks_in_flight{deployment=~\"$deployment\"}, datatype)",
        "refresh": 2,
        "regex": "",
        "skipUrlSync": false,
        "sort": 0,
        "tagValuesQuery": "",
        "tags": [],
        "tagsQuery": "",
        "type": "query",
        "useTags": false
      }
    ]
  },
  "time": {
    "from": "now-24h",
    "to": "now"
  },
  "timepicker": {
    "refresh_intervals": [
      "5s",
      "10s",
      "30s",
      "1m",
      "5m",
      "15m",
      "30m",
      "1h",
      "2h",
      "1d"
    ],
    "time_options": [
      "5m",
      "15m",
      "1h",
      "6h",
      "12h",
      "24h",
      "2d",
      "7d",
      "30d"
    ]
  },
  "timezone": "utc",
  "title": "Pipeline: Gardener",
  "uid": "eBbUW6oik",
  "version":61
}
