{
  "annotations": {
    "list": [
      {
        "$$hashKey": "object:405",
        "builtIn": 1,
        "datasource": "-- Grafana --",
        "enable": false,
        "hide": true,
        "iconColor": "rgba(0, 211, 255, 1)",
        "name": "Annotations & Alerts",
        "type": "dashboard"
      }
    ]
  },
  "editable": false,
  "gnetId": null,
  "graphTooltip": 0,
  "id": 37,
  "iteration": 1539196193199,
  "links": [],
  "panels": [
    {
      "collapsed": false,
      "gridPos": {
        "h": 1,
        "w": 24,
        "x": 0,
        "y": 0
      },
      "id": 37,
      "panels": [],
      "repeat": null,
      "title": "Errors - $service",
      "type": "row"
    },
    {
      "aliasColors": {},
      "bars": false,
      "dashLength": 10,
      "dashes": false,
      "datasource": "$datasource",
      "editable": false,
      "error": false,
      "fill": 1,
      "gridPos": {
        "h": 7,
        "w": 8,
        "x": 0,
        "y": 1
      },
      "id": 17,
      "isNew": false,
      "legend": {
        "alignAsTable": false,
        "avg": false,
        "current": false,
        "hideEmpty": false,
        "hideZero": false,
        "max": false,
        "min": false,
        "rightSide": false,
        "show": false,
        "total": false,
        "values": false
      },
      "lines": true,
      "linewidth": 1,
      "links": [],
      "minSpan": 8,
      "nullPointMode": "null",
      "percentage": false,
      "pointradius": 5,
      "points": false,
      "renderer": "flot",
      "seriesOverrides": [],
      "spaceLength": 10,
      "stack": false,
      "steppedLine": false,
      "targets": [
        {
          "$$hashKey": "object:567",
          "expr": "sum by(phase, status, retries, service)(increase(etl_gcs_retry_count{service=~\"$service\", table=~\"$table\"}[$interval]))",
          "format": "time_series",
          "hide": false,
          "intervalFactor": 2,
          "legendFormat": "{{phase}} : {{status}} : {{retries}} : {{service}}",
          "refId": "A",
          "step": 120
        },
        {
          "$$hashKey": "object:568",
          "expr": "sum by(kind, service) (rate(etl_backend_failure_count{service=~\"$service\", table=~\"$table\"}[5m]))",
          "format": "time_series",
          "hide": false,
          "intervalFactor": 2,
          "legendFormat": "{{kind}} : {{service}}",
          "refId": "B"
        }
      ],
      "thresholds": [],
      "timeFrom": null,
      "timeShift": null,
      "title": "Storage Errors [$interval]",
      "tooltip": {
        "shared": true,
        "sort": 0,
        "value_type": "individual"
      },
      "transparent": false,
      "type": "graph",
      "xaxis": {
        "buckets": null,
        "format": "",
        "logBase": 0,
        "mode": "time",
        "name": null,
        "show": true,
        "values": []
      },
      "yaxes": [
        {
          "format": "short",
          "logBase": 1,
          "min": 0,
          "show": true
        },
        {
          "format": "short",
          "logBase": 1,
          "show": true
        }
      ],
      "yaxis": {
        "align": false,
        "alignLevel": null
      }
    },
    {
      "aliasColors": {},
      "bars": false,
      "dashLength": 10,
      "dashes": false,
      "datasource": "$datasource",
      "editable": false,
      "error": false,
      "fill": 1,
      "gridPos": {
        "h": 7,
        "w": 8,
        "x": 8,
        "y": 1
      },
      "id": 26,
      "isNew": false,
      "legend": {
        "alignAsTable": false,
        "avg": false,
        "current": false,
        "hideEmpty": false,
        "hideZero": false,
        "max": false,
        "min": false,
        "rightSide": false,
        "show": false,
        "total": false,
        "values": false
      },
      "lines": true,
      "linewidth": 1,
      "links": [],
      "nullPointMode": "null",
      "percentage": false,
      "pointradius": 5,
      "points": false,
      "renderer": "flot",
      "seriesOverrides": [],
      "spaceLength": 10,
      "stack": false,
      "steppedLine": false,
      "targets": [
        {
          "$$hashKey": "object:986",
          "expr": "sum by(filetype, kind, service, table)(increase(etl_error_count{service=~\"$service\", table=~\"$table\"}[$interval]))",
          "format": "time_series",
          "intervalFactor": 1,
          "legendFormat": "Error {{filetype}} : {{kind}} : {{service}} : {{table}}",
          "refId": "A",
          "step": 60
        }
      ],
      "thresholds": [],
      "timeFrom": null,
      "timeShift": null,
      "title": "Test Error Count by Type/Status [$interval]",
      "tooltip": {
        "shared": true,
        "sort": 0,
        "value_type": "individual"
      },
      "transparent": false,
      "type": "graph",
      "xaxis": {
        "buckets": null,
        "format": "",
        "logBase": 0,
        "mode": "time",
        "name": null,
        "show": true,
        "values": []
      },
      "yaxes": [
        {
          "format": "short",
          "logBase": 1,
          "min": 0,
          "show": true
        },
        {
          "format": "short",
          "logBase": 1,
          "show": true
        }
      ],
      "yaxis": {
        "align": false,
        "alignLevel": null
      }
    },
    {
      "aliasColors": {},
      "bars": false,
      "dashLength": 10,
      "dashes": false,
      "datasource": "$datasource",
      "description": "",
      "fill": 1,
      "gridPos": {
        "h": 7,
        "w": 8,
        "x": 16,
        "y": 1
      },
      "id": 36,
      "legend": {
        "avg": false,
        "current": false,
        "max": false,
        "min": false,
        "show": false,
        "total": false,
        "values": false
      },
      "lines": true,
      "linewidth": 1,
      "links": [],
      "nullPointMode": "null",
      "percentage": false,
      "pointradius": 5,
      "points": false,
      "renderer": "flot",
      "seriesOverrides": [],
      "spaceLength": 10,
      "stack": false,
      "steppedLine": false,
      "targets": [
        {
          "$$hashKey": "object:1280",
          "expr": "sum by(service) (increase(etl_annotator_Annotation_Time_Summary_count{service=~\"$service\"}[$interval]))",
          "format": "time_series",
          "intervalFactor": 2,
          "legendFormat": "Requests : {{service}}",
          "refId": "A"
        },
        {
          "$$hashKey": "object:1281",
          "expr": "sum by(source, service)(increase(etl_annotator_Error_Count{service=~\"$service\"}[$interval]))",
          "format": "time_series",
          "hide": false,
          "intervalFactor": 2,
          "legendFormat": "Errors: {{source}}",
          "refId": "B"
        }
      ],
      "thresholds": [],
      "timeFrom": null,
      "timeShift": null,
      "title": "Annotator Stats",
      "tooltip": {
        "shared": true,
        "sort": 0,
        "value_type": "individual"
      },
      "type": "graph",
      "xaxis": {
        "buckets": null,
        "mode": "time",
        "name": null,
        "show": true,
        "values": []
      },
      "yaxes": [
        {
          "format": "short",
          "label": null,
          "logBase": 10,
          "max": null,
          "min": null,
          "show": true
        },
        {
          "format": "short",
          "label": null,
          "logBase": 1,
          "max": null,
          "min": null,
          "show": true
        }
      ],
      "yaxis": {
        "align": false,
        "alignLevel": null
      }
    },
    {
      "collapsed": false,
      "gridPos": {
        "h": 1,
        "w": 24,
        "x": 0,
        "y": 8
      },
      "id": 38,
      "panels": [],
      "repeat": null,
      "title": "Uptime, RAM, CPU - $service",
      "type": "row"
    },
    {
      "aliasColors": {},
      "bars": false,
      "dashLength": 10,
      "dashes": false,
      "datasource": "$datasource",
      "editable": false,
      "error": false,
      "fill": 1,
      "gridPos": {
        "h": 8,
        "w": 8,
        "x": 0,
        "y": 9
      },
      "id": 15,
      "isNew": false,
      "legend": {
        "alignAsTable": false,
        "avg": false,
        "current": false,
        "hideEmpty": false,
        "hideZero": false,
        "max": false,
        "min": false,
        "rightSide": false,
        "show": false,
        "total": false,
        "values": false
      },
      "lines": true,
      "linewidth": 1,
      "links": [],
      "nullPointMode": "null",
      "percentage": false,
      "pointradius": 5,
      "points": false,
      "renderer": "flot",
      "seriesOverrides": [
        {
          "alias": "Instances",
          "color": "#64B0C8",
          "fill": 0,
          "linewidth": 4,
          "yaxis": 2
        }
      ],
      "spaceLength": 10,
      "stack": false,
      "steppedLine": false,
      "targets": [
        {
          "$$hashKey": "object:1444",
          "expr": "sum by(instance)(time()-process_start_time_seconds{service=~\"$service\"})",
          "format": "time_series",
          "intervalFactor": 2,
          "legendFormat": "{{instance}}",
          "refId": "A",
          "step": 120
        },
        {
          "$$hashKey": "object:1445",
          "expr": "$show_count(count by(service) (process_start_time_seconds{service=~\"$service\"}))",
          "format": "time_series",
          "intervalFactor": 2,
          "legendFormat": "Instances",
          "refId": "B",
          "step": 120
        }
      ],
      "thresholds": [],
      "timeFrom": null,
      "timeShift": null,
      "title": "Uptime - Per-instance",
      "tooltip": {
        "shared": true,
        "sort": 2,
        "value_type": "individual"
      },
      "transparent": false,
      "type": "graph",
      "xaxis": {
        "buckets": null,
        "format": "",
        "logBase": 0,
        "mode": "time",
        "name": null,
        "show": true,
        "values": []
      },
      "yaxes": [
        {
          "format": "dtdurations",
          "logBase": 10,
          "min": 60,
          "show": true
        },
        {
          "decimals": null,
          "format": "short",
          "logBase": 1,
          "max": null,
          "min": 0,
          "show": true
        }
      ],
      "yaxis": {
        "align": false,
        "alignLevel": null
      }
    },
    {
      "aliasColors": {},
      "bars": false,
      "dashLength": 10,
      "dashes": false,
      "datasource": "$datasource",
      "editable": false,
      "error": false,
      "fill": 1,
      "gridPos": {
        "h": 8,
        "w": 8,
        "x": 8,
        "y": 9
      },
      "id": 2,
      "isNew": false,
      "legend": {
        "alignAsTable": false,
        "avg": false,
        "current": false,
        "hideEmpty": true,
        "hideZero": true,
        "max": false,
        "min": false,
        "rightSide": false,
        "show": false,
        "total": false,
        "values": false
      },
      "lines": true,
      "linewidth": 1,
      "links": [],
      "nullPointMode": "null",
      "percentage": false,
      "pointradius": 5,
      "points": false,
      "renderer": "flot",
      "seriesOverrides": [
        {
          "alias": "/Instances/",
          "color": "#6ed0e0",
          "fill": 0,
          "linewidth": 4,
          "yaxis": 2
        },
        {
          "alias": "/Average/",
          "color": "#7eb26d",
          "fill": 0,
          "linewidth": 2
        },
        {
          "alias": "/inst .*/",
          "color": "rgba(115, 115, 115, 0.55)",
          "fill": 0
        }
      ],
      "spaceLength": 10,
      "stack": false,
      "steppedLine": false,
      "targets": [
        {
          "$$hashKey": "object:1576",
          "expr": "sum by(instance) (process_resident_memory_bytes{service=~\"$service\"})",
          "format": "time_series",
          "interval": "60s",
          "intervalFactor": 1,
          "legendFormat": "inst {{instance}}",
          "refId": "A",
          "step": 60
        },
        {
          "$$hashKey": "object:1577",
          "expr": "$show_count (count by(service) (process_start_time_seconds{service=~\"$service\"}))",
          "format": "time_series",
          "hide": false,
          "intervalFactor": 2,
          "legendFormat": "Instances: {{service}}",
          "refId": "B"
        },
        {
          "$$hashKey": "object:1578",
          "expr": "avg by(service) (process_resident_memory_bytes{service=~\"$service\"})",
          "format": "time_series",
          "intervalFactor": 2,
          "legendFormat": "Average: {{service}}",
          "refId": "C"
        }
      ],
      "thresholds": [],
      "timeFrom": null,
      "timeShift": null,
      "title": "RAM - Process Resident Memory",
      "tooltip": {
        "shared": false,
        "sort": 2,
        "value_type": "individual"
      },
      "transparent": false,
      "type": "graph",
      "xaxis": {
        "buckets": null,
        "format": "",
        "logBase": 0,
        "mode": "time",
        "name": null,
        "show": true,
        "values": []
      },
      "yaxes": [
        {
          "format": "decbytes",
          "logBase": 1,
          "show": true
        },
        {
          "decimals": 0,
          "format": "short",
          "logBase": 1,
          "min": "0",
          "show": true
        }
      ],
      "yaxis": {
        "align": false,
        "alignLevel": null
      }
    },
    {
      "aliasColors": {},
      "bars": false,
      "dashLength": 10,
      "dashes": false,
      "datasource": "$datasource",
      "editable": false,
      "error": false,
      "fill": 1,
      "gridPos": {
        "h": 8,
        "w": 8,
        "x": 16,
        "y": 9
      },
      "id": 4,
      "isNew": false,
      "legend": {
        "alignAsTable": false,
        "avg": false,
        "current": false,
        "hideEmpty": false,
        "hideZero": false,
        "max": false,
        "min": false,
        "rightSide": false,
        "show": false,
        "total": false,
        "values": false
      },
      "lines": true,
      "linewidth": 1,
      "links": [],
      "nullPointMode": "null",
      "percentage": false,
      "pointradius": 5,
      "points": false,
      "renderer": "flot",
      "seriesOverrides": [
        {
          "alias": "Instances",
          "color": "#6ed0e0",
          "fill": 0,
          "linewidth": 4,
          "yaxis": 2
        },
        {
          "alias": "/avg .*/",
          "color": "#7eb26d",
          "fill": 0,
          "linewidth": 2
        },
        {
          "alias": "/inst .*/",
          "color": "rgba(115, 115, 115, 0.55)",
          "fill": 0
        }
      ],
      "spaceLength": 10,
      "stack": false,
      "steppedLine": false,
      "targets": [
        {
          "$$hashKey": "object:1674",
          "expr": "rate(process_cpu_seconds_total{service=~\"$service\"}[2m])/2",
          "format": "time_series",
          "interval": "60s",
          "intervalFactor": 1,
          "legendFormat": "inst {{instance}}",
          "refId": "A",
          "step": 60
        },
        {
          "$$hashKey": "object:1675",
          "expr": "avg(rate(process_cpu_seconds_total{service=~\"$service\"}[5m])/2)",
          "format": "time_series",
          "interval": "60s",
          "intervalFactor": 1,
          "legendFormat": "avg {{instance}}",
          "refId": "C",
          "step": 60
        },
        {
          "$$hashKey": "object:1676",
          "expr": "$show_count(count by(service) (process_start_time_seconds{service=~\"$service\"}))",
          "format": "time_series",
          "hide": false,
          "interval": "60s",
          "intervalFactor": 1,
          "legendFormat": "Instances",
          "refId": "B"
        }
      ],
      "thresholds": [],
      "timeFrom": null,
      "timeShift": null,
      "title": "CPU - Per-instance & Avg",
      "tooltip": {
        "shared": true,
        "sort": 2,
        "value_type": "individual"
      },
      "transparent": false,
      "type": "graph",
      "xaxis": {
        "buckets": null,
        "format": "",
        "logBase": 0,
        "mode": "time",
        "name": null,
        "show": true,
        "values": []
      },
      "yaxes": [
        {
          "decimals": null,
          "format": "percentunit",
          "label": "CPU %",
          "logBase": 1,
          "max": null,
          "min": "0",
          "show": true
        },
        {
          "decimals": 0,
          "format": "short",
          "label": "Instance Count",
          "logBase": 1,
          "max": null,
          "min": "0",
          "show": true
        }
      ],
      "yaxis": {
        "align": false,
        "alignLevel": null
      }
    },
    {
      "collapsed": false,
      "gridPos": {
        "h": 1,
        "w": 24,
        "x": 0,
        "y": 17
      },
      "id": 39,
      "panels": [],
      "repeat": null,
      "title": "Worker Aggregates - $service",
      "type": "row"
    },
    {
      "aliasColors": {},
      "bars": false,
      "dashLength": 10,
      "dashes": false,
      "datasource": "$datasource",
      "editable": false,
      "error": false,
      "fill": 1,
      "gridPos": {
        "h": 7,
        "w": 8,
        "x": 0,
        "y": 18
      },
      "id": 14,
      "isNew": false,
      "legend": {
        "alignAsTable": false,
        "avg": false,
        "current": false,
        "hideEmpty": false,
        "hideZero": false,
        "max": false,
        "min": false,
        "rightSide": false,
        "show": false,
        "total": false,
        "values": false
      },
      "lines": true,
      "linewidth": 1,
      "nullPointMode": "null",
      "percentage": false,
      "pointradius": 5,
      "points": false,
      "renderer": "flot",
      "seriesOverrides": [
        {
          "alias": "sum"
        }
      ],
      "spaceLength": 10,
      "stack": false,
      "steppedLine": false,
      "targets": [
        {
          "$$hashKey": "object:1780",
          "expr": "etl_worker_count{service=~\"$service\", table=~\"$table\"}",
          "format": "time_series",
          "interval": "60s",
          "intervalFactor": 1,
          "legendFormat": "{{instance}}",
          "refId": "A",
          "step": 60
        },
        {
          "$$hashKey": "object:1781",
          "expr": "sum by(service) (etl_worker_count{service=~\"$service\", table=~\"$table\"})",
          "format": "time_series",
          "interval": "60s",
          "intervalFactor": 1,
          "legendFormat": "sum : {{service}}",
          "refId": "B"
        }
      ],
      "thresholds": [],
      "timeFrom": null,
      "timeShift": null,
      "title": "Worker Count By Instance",
      "tooltip": {
        "shared": true,
        "sort": 2,
        "value_type": "individual"
      },
      "transparent": false,
      "type": "graph",
      "xaxis": {
        "buckets": null,
        "format": "",
        "logBase": 0,
        "mode": "time",
        "name": null,
        "show": true,
        "values": []
      },
      "yaxes": [
        {
          "format": "short",
          "logBase": 1,
          "show": true
        },
        {
          "format": "short",
          "logBase": 1,
          "show": true
        }
      ],
      "yaxis": {
        "align": false,
        "alignLevel": null
      }
    },
    {
      "aliasColors": {},
      "bars": false,
      "dashLength": 10,
      "dashes": false,
      "datasource": "$datasource",
      "editable": false,
      "error": false,
      "fill": 1,
      "gridPos": {
        "h": 7,
        "w": 8,
        "x": 8,
        "y": 18
      },
      "id": 1,
      "isNew": false,
      "legend": {
        "alignAsTable": false,
        "avg": false,
        "current": false,
        "hideEmpty": false,
        "hideZero": false,
        "max": false,
        "min": false,
        "rightSide": false,
        "show": false,
        "total": false,
        "values": false
      },
      "lines": true,
      "linewidth": 1,
      "nullPointMode": "null",
      "percentage": false,
      "pointradius": 5,
      "points": false,
      "renderer": "flot",
      "seriesOverrides": [],
      "spaceLength": 10,
      "stack": false,
      "steppedLine": false,
      "targets": [
        {
          "$$hashKey": "object:1856",
          "expr": "sum by(state, service)(etl_worker_state{service=~\"$service\", table=~\"$table\"})",
          "format": "time_series",
          "interval": "60s",
          "intervalFactor": 1,
          "legendFormat": "{{state}}",
          "refId": "A",
          "step": 60
        }
      ],
      "thresholds": [],
      "timeFrom": null,
      "timeShift": null,
      "title": "Worker States",
      "tooltip": {
        "shared": true,
        "sort": 2,
        "value_type": "individual"
      },
      "transparent": false,
      "type": "graph",
      "xaxis": {
        "buckets": null,
        "format": "",
        "logBase": 0,
        "mode": "time",
        "name": null,
        "show": true,
        "values": []
      },
      "yaxes": [
        {
          "format": "short",
          "logBase": 1,
          "show": true
        },
        {
          "format": "short",
          "logBase": 1,
          "show": true
        }
      ],
      "yaxis": {
        "align": false,
        "alignLevel": null
      }
    },
    {
      "aliasColors": {},
      "bars": false,
      "dashLength": 10,
      "dashes": false,
      "datasource": "$datasource",
      "fill": 1,
      "gridPos": {
        "h": 7,
        "w": 8,
        "x": 16,
        "y": 18
      },
      "id": 27,
      "legend": {
        "avg": false,
        "current": false,
        "max": false,
        "min": false,
        "show": false,
        "total": false,
        "values": false
      },
      "lines": true,
      "linewidth": 1,
      "links": [],
      "nullPointMode": "null",
      "percentage": false,
      "pointradius": 5,
      "points": false,
      "renderer": "flot",
      "seriesOverrides": [],
      "spaceLength": 10,
      "stack": false,
      "steppedLine": false,
      "targets": [
        {
          "$$hashKey": "object:1910",
          "expr": "sum by(version, status, service) (irate(etl_worker_duration_seconds_count{service=~\"$service\"}[4m]))",
          "format": "time_series",
          "interval": "",
          "intervalFactor": 1,
          "legendFormat": "{{status}}",
          "refId": "F"
        }
      ],
      "thresholds": [],
      "timeFrom": null,
      "timeShift": null,
      "title": "Worker QPS",
      "tooltip": {
        "shared": true,
        "sort": 2,
        "value_type": "individual"
      },
      "type": "graph",
      "xaxis": {
        "buckets": null,
        "mode": "time",
        "name": null,
        "show": true,
        "values": []
      },
      "yaxes": [
        {
          "decimals": 2,
          "format": "none",
          "label": "QPS",
          "logBase": 1,
          "max": null,
          "min": "0",
          "show": true
        },
        {
          "format": "short",
          "label": null,
          "logBase": 1,
          "max": null,
          "min": null,
          "show": true
        }
      ],
      "yaxis": {
        "align": false,
        "alignLevel": null
      }
    },
    {
      "collapsed": false,
      "gridPos": {
        "h": 1,
        "w": 24,
        "x": 0,
        "y": 25
      },
      "id": 40,
      "panels": [],
      "repeat": null,
      "title": "Task archive & Test files - $service",
      "type": "row"
    },
    {
      "aliasColors": {},
      "bars": false,
      "dashLength": 10,
      "dashes": false,
      "datasource": "$datasource",
      "editable": false,
      "error": false,
      "fill": 1,
      "gridPos": {
        "h": 7,
        "w": 8,
        "x": 0,
        "y": 26
      },
      "id": 12,
      "isNew": false,
      "legend": {
        "alignAsTable": false,
        "avg": false,
        "current": false,
        "hideEmpty": false,
        "hideZero": false,
        "max": false,
        "min": false,
        "rightSide": false,
        "show": false,
        "total": false,
        "values": false
      },
      "lines": true,
      "linewidth": 1,
      "nullPointMode": "null",
      "percentage": false,
      "pointradius": 5,
      "points": false,
      "renderer": "flot",
      "seriesOverrides": [
        {
          "alias": "Instances",
          "color": "#65c5db",
          "fill": 0,
          "linewidth": 3,
          "yaxis": 2
        }
      ],
      "spaceLength": 10,
      "stack": false,
      "steppedLine": false,
      "targets": [
        {
          "$$hashKey": "object:2041",
          "expr": "sum by(status, version, service)(rate(etl_task_count{service=~\"$service\", table=~\"$table|unknown\"}[$interval]))",
          "format": "time_series",
          "intervalFactor": 1,
          "legendFormat": "{{version}} : {{status}}",
          "refId": "A",
          "step": 60
        },
        {
          "$$hashKey": "object:2042",
          "expr": "$show_count(count by(service) (process_start_time_seconds{service=~\"$service\"}))",
          "format": "time_series",
          "intervalFactor": 2,
          "legendFormat": "Instances",
          "refId": "B"
        }
      ],
      "thresholds": [],
      "timeFrom": null,
      "timeShift": null,
      "title": "Task Totals by Version / Status [$interval]",
      "tooltip": {
        "shared": true,
        "sort": 2,
        "value_type": "individual"
      },
      "transparent": false,
      "type": "graph",
      "xaxis": {
        "buckets": null,
        "format": "",
        "logBase": 0,
        "mode": "time",
        "name": null,
        "show": true,
        "values": []
      },
      "yaxes": [
        {
          "decimals": 2,
          "format": "short",
          "logBase": 1,
          "max": null,
          "min": "0",
          "show": true
        },
        {
          "decimals": null,
          "format": "short",
          "logBase": 1,
          "min": "0",
          "show": true
        }
      ],
      "yaxis": {
        "align": false,
        "alignLevel": null
      }
    },
    {
      "aliasColors": {},
      "bars": false,
      "dashLength": 10,
      "dashes": false,
      "datasource": "$datasource",
      "editable": false,
      "error": false,
      "fill": 1,
      "gridPos": {
        "h": 7,
        "w": 8,
        "x": 8,
        "y": 26
      },
      "id": 3,
      "isNew": false,
      "legend": {
        "alignAsTable": false,
        "avg": false,
        "current": false,
        "hideEmpty": false,
        "hideZero": false,
        "max": false,
        "min": false,
        "rightSide": false,
        "show": false,
        "total": false,
        "values": false
      },
      "lines": true,
      "linewidth": 1,
      "nullPointMode": "null",
      "percentage": false,
      "pointradius": 5,
      "points": false,
      "renderer": "flot",
      "seriesOverrides": [],
      "spaceLength": 10,
      "stack": false,
      "steppedLine": false,
      "targets": [
        {
          "$$hashKey": "object:2117",
          "expr": "sum by(status, service)(60*irate(etl_task_count{service=~\"$service\", table=~\"$table\"}[4m]))",
          "format": "time_series",
          "interval": "60s",
          "intervalFactor": 1,
          "legendFormat": "{{status}}",
          "refId": "A",
          "step": 60
        }
      ],
      "thresholds": [],
      "timeFrom": null,
      "timeShift": null,
      "title": "Tasks/Min by Status",
      "tooltip": {
        "shared": true,
        "sort": 2,
        "value_type": "individual"
      },
      "transparent": false,
      "type": "graph",
      "xaxis": {
        "buckets": null,
        "format": "",
        "logBase": 0,
        "mode": "time",
        "name": null,
        "show": true,
        "values": []
      },
      "yaxes": [
        {
          "format": "short",
          "logBase": 1,
          "min": "0",
          "show": true
        },
        {
          "format": "short",
          "logBase": 1,
          "show": true
        }
      ],
      "yaxis": {
        "align": false,
        "alignLevel": null
      }
    },
    {
      "aliasColors": {},
      "bars": false,
      "dashLength": 10,
      "dashes": false,
      "datasource": "$datasource",
      "editable": false,
      "error": false,
      "fill": 1,
      "gridPos": {
        "h": 7,
        "w": 8,
        "x": 16,
        "y": 26
      },
      "id": 13,
      "isNew": false,
      "legend": {
        "alignAsTable": false,
        "avg": false,
        "current": false,
        "hideEmpty": false,
        "hideZero": false,
        "max": false,
        "min": false,
        "rightSide": false,
        "show": false,
        "total": false,
        "values": false
      },
      "lines": true,
      "linewidth": 1,
      "nullPointMode": "null as zero",
      "percentage": false,
      "pointradius": 5,
      "points": false,
      "renderer": "flot",
      "seriesOverrides": [],
      "spaceLength": 10,
      "stack": true,
      "steppedLine": false,
      "targets": [
        {
          "$$hashKey": "object:4819",
          "expr": "60*irate(etl_task_count{service=\"$service\", table=~\"$table\", status=\"OK\"}[5m])",
          "format": "time_series",
          "hide": false,
          "interval": "60s",
          "intervalFactor": 1,
          "legendFormat": "{{instance}}",
          "refId": "B",
          "step": 60
        },
        {
          "$$hashKey": "object:4873",
          "expr": "# NOTE: query above deliberately does not match the service as a regex. We do this to disable the display for All parsers.",
          "format": "time_series",
          "hide": true,
          "intervalFactor": 1,
          "refId": "A"
        }
      ],
      "thresholds": [],
      "timeFrom": null,
      "timeShift": null,
      "title": "Successful Tasks/Min by Instance",
      "tooltip": {
        "shared": true,
        "sort": 2,
        "value_type": "individual"
      },
      "transparent": false,
      "type": "graph",
      "xaxis": {
        "buckets": null,
        "format": "",
        "logBase": 0,
        "mode": "time",
        "name": null,
        "show": true,
        "values": []
      },
      "yaxes": [
        {
          "format": "short",
          "logBase": 1,
          "min": 0,
          "show": true
        },
        {
          "format": "short",
          "logBase": 1,
          "show": true
        }
      ],
      "yaxis": {
        "align": false,
        "alignLevel": null
      }
    },
    {
      "aliasColors": {},
      "bars": false,
      "dashLength": 10,
      "dashes": false,
      "datasource": "$datasource",
      "editable": false,
      "error": false,
      "fill": 1,
      "gridPos": {
        "h": 7,
        "w": 8,
        "x": 0,
        "y": 33
      },
      "id": 6,
      "isNew": false,
      "legend": {
        "alignAsTable": false,
        "avg": false,
        "current": false,
        "hideEmpty": false,
        "hideZero": false,
        "max": false,
        "min": false,
        "rightSide": false,
        "show": false,
        "total": false,
        "values": false
      },
      "lines": true,
      "linewidth": 1,
      "nullPointMode": "null",
      "percentage": false,
      "pointradius": 5,
      "points": false,
      "renderer": "flot",
      "seriesOverrides": [],
      "spaceLength": 10,
      "stack": false,
      "steppedLine": false,
      "targets": [
        {
          "$$hashKey": "object:2225",
          "expr": "sum by(filetype, status, service)(irate(etl_test_count{service=~\"$service\", table=~\"$table\", filetype!=\"meta\"}[4m]))",
          "format": "time_series",
          "interval": "",
          "intervalFactor": 1,
          "legendFormat": "{{filetype}} : {{status}} : {{service}}",
          "refId": "A",
          "step": 60
        }
      ],
      "thresholds": [],
      "timeFrom": null,
      "timeShift": null,
      "title": "Tests/Sec by Type",
      "tooltip": {
        "shared": true,
        "sort": 2,
        "value_type": "individual"
      },
      "transparent": false,
      "type": "graph",
      "xaxis": {
        "buckets": null,
        "format": "",
        "logBase": 0,
        "mode": "time",
        "name": null,
        "show": true,
        "values": []
      },
      "yaxes": [
        {
          "format": "short",
          "logBase": 1,
          "show": true
        },
        {
          "format": "short",
          "logBase": 1,
          "show": true
        }
      ],
      "yaxis": {
        "align": false,
        "alignLevel": null
      }
    },
    {
      "aliasColors": {},
      "bars": false,
      "dashLength": 10,
      "dashes": false,
      "datasource": "$datasource",
      "editable": false,
      "error": false,
      "fill": 1,
      "gridPos": {
        "h": 7,
        "w": 8,
        "x": 8,
        "y": 33
      },
      "id": 16,
      "isNew": false,
      "legend": {
        "alignAsTable": false,
        "avg": false,
        "current": false,
        "hideEmpty": false,
        "hideZero": false,
        "max": false,
        "min": false,
        "rightSide": false,
        "show": false,
        "total": false,
        "values": false
      },
      "lines": true,
      "linewidth": 1,
      "nullPointMode": "null",
      "percentage": false,
      "pointradius": 5,
      "points": false,
      "renderer": "flot",
      "seriesOverrides": [],
      "spaceLength": 10,
      "stack": false,
      "steppedLine": false,
      "targets": [
        {
          "$$hashKey": "object:2279",
          "expr": "sum by(version, filetype, status, service)(increase(etl_test_count{service=~\"$service\", table=~\"$table\"}[$interval]))",
          "format": "time_series",
          "interval": "60s",
          "intervalFactor": 1,
          "legendFormat": "{{version}} : {{filetype}} : {{status}} : {{service}}",
          "refId": "A",
          "step": 60
        }
      ],
      "thresholds": [],
      "timeFrom": null,
      "timeShift": null,
      "title": "Test Count by Type [$interval]",
      "tooltip": {
        "shared": true,
        "sort": 2,
        "value_type": "individual"
      },
      "transparent": false,
      "type": "graph",
      "xaxis": {
        "buckets": null,
        "format": "",
        "logBase": 0,
        "mode": "time",
        "name": null,
        "show": true,
        "values": []
      },
      "yaxes": [
        {
          "format": "short",
          "logBase": 1,
          "show": true
        },
        {
          "format": "short",
          "logBase": 1,
          "show": true
        }
      ],
      "yaxis": {
        "align": false,
        "alignLevel": null
      }
    },
    {
      "aliasColors": {},
      "bars": false,
      "dashLength": 10,
      "dashes": false,
      "datasource": "$datasource",
      "editable": false,
      "error": false,
      "fill": 1,
      "gridPos": {
        "h": 7,
        "w": 8,
        "x": 16,
        "y": 33
      },
      "id": 25,
      "isNew": false,
      "legend": {
        "alignAsTable": false,
        "avg": false,
        "current": false,
        "hideEmpty": false,
        "hideZero": false,
        "max": false,
        "min": false,
        "rightSide": false,
        "show": false,
        "total": false,
        "values": false
      },
      "lines": true,
      "linewidth": 1,
      "nullPointMode": "null",
      "percentage": false,
      "pointradius": 5,
      "points": false,
      "renderer": "flot",
      "seriesOverrides": [],
      "spaceLength": 10,
      "stack": false,
      "steppedLine": false,
      "targets": [
        {
          "$$hashKey": "object:2333",
          "expr": "sum by(filetype, kind, service)(increase(etl_warning_count{service=~\"$service\", table=~\"$table\"}[$interval]))",
          "format": "time_series",
          "intervalFactor": 2,
          "legendFormat": "Warning {{filetype}} : {{kind}} : {{service}}",
          "refId": "B",
          "step": 120
        }
      ],
      "thresholds": [],
      "timeFrom": null,
      "timeShift": null,
      "title": "Test Warning Count by Table/Type/Status [$interval]",
      "tooltip": {
        "shared": true,
        "sort": 2,
        "value_type": "individual"
      },
      "transparent": false,
      "type": "graph",
      "xaxis": {
        "buckets": null,
        "format": "",
        "logBase": 0,
        "mode": "time",
        "name": null,
        "show": true,
        "values": []
      },
      "yaxes": [
        {
          "format": "short",
          "logBase": 1,
          "show": true
        },
        {
          "format": "short",
          "logBase": 1,
          "show": true
        }
      ],
      "yaxis": {
        "align": false,
        "alignLevel": null
      }
    },
    {
      "collapsed": false,
      "gridPos": {
        "h": 1,
        "w": 24,
        "x": 0,
        "y": 40
      },
      "id": 41,
      "panels": [],
      "repeat": null,
      "title": "Performance - $service",
      "type": "row"
    },
    {
      "aliasColors": {},
      "bars": false,
      "dashLength": 10,
      "dashes": false,
      "datasource": "$datasource",
      "editable": false,
      "error": false,
      "fill": 1,
      "gridPos": {
        "h": 7,
        "w": 12,
        "x": 0,
        "y": 41
      },
      "id": 9,
      "isNew": false,
      "legend": {
        "alignAsTable": false,
        "avg": false,
        "current": false,
        "hideEmpty": true,
        "hideZero": true,
        "max": false,
        "min": false,
        "rightSide": false,
        "show": false,
        "total": false,
        "values": false
      },
      "lines": true,
      "linewidth": 1,
      "links": [],
      "nullPointMode": "null",
      "percentage": false,
      "pointradius": 5,
      "points": false,
      "renderer": "flot",
      "seriesOverrides": [
        {
          "alias": "Instances",
          "color": "#65c5db",
          "fill": 0,
          "linewidth": 4,
          "yaxis": 2
        }
      ],
      "spaceLength": 10,
      "stack": false,
      "steppedLine": false,
      "targets": [
        {
          "$$hashKey": "object:2396",
          "expr": "histogram_quantile(0.99, sum by(le, status, service) (rate(etl_insertion_time_seconds_bucket{service=~\"$service\"}[5m])))",
          "format": "time_series",
          "intervalFactor": 1,
          "legendFormat": "{{status}} 0.99",
          "refId": "A",
          "step": 60
        },
        {
          "$$hashKey": "object:2397",
          "expr": "histogram_quantile(0.95, sum by(le, status, service) (rate(etl_insertion_time_seconds_bucket{service=~\"$service\"}[5m])))",
          "format": "time_series",
          "intervalFactor": 1,
          "legendFormat": "{{status}} 0.95",
          "refId": "B",
          "step": 60
        },
        {
          "$$hashKey": "object:2398",
          "expr": "(sum by(le, status) (rate(etl_insertion_time_seconds_sum{service=~\"$service\"}[5m]))) / (sum by(le, status, service)(rate(etl_insertion_time_seconds_count{service=~\"$service\"}[5m])))",
          "format": "time_series",
          "intervalFactor": 1,
          "legendFormat": "{{status}} average",
          "refId": "F",
          "step": 60
        },
        {
          "$$hashKey": "object:2399",
          "expr": "histogram_quantile(0.5, sum by(le, status, service) (rate(etl_insertion_time_seconds_bucket{service=~\"$service\"}[5m])))",
          "format": "time_series",
          "intervalFactor": 1,
          "legendFormat": "{{status}} 0.5",
          "refId": "C",
          "step": 60
        },
        {
          "$$hashKey": "object:2400",
          "expr": "histogram_quantile(0.25, sum by(le, status, service) (rate(etl_insertion_time_seconds_bucket{service=~\"$service\"}[5m])))",
          "format": "time_series",
          "intervalFactor": 1,
          "legendFormat": "{{status}} 0.25",
          "refId": "D",
          "step": 60
        },
        {
          "$$hashKey": "object:2401",
          "expr": "histogram_quantile(0.05, sum by(le, status, service) (rate(etl_insertion_time_seconds_bucket{service=~\"$service\"}[5m])))",
          "format": "time_series",
          "intervalFactor": 1,
          "legendFormat": "{{status}} 0.05",
          "refId": "E",
          "step": 60
        },
        {
          "$$hashKey": "object:2402",
          "expr": "$show_count(count by(service) (process_start_time_seconds{service=~\"$service\"}))",
          "format": "time_series",
          "intervalFactor": 2,
          "legendFormat": "Instances",
          "refId": "G"
        }
      ],
      "thresholds": [],
      "timeFrom": null,
      "timeShift": null,
      "title": "BQ Insertion Time Percentiles",
      "tooltip": {
        "shared": true,
        "sort": 0,
        "value_type": "individual"
      },
      "transparent": false,
      "type": "graph",
      "xaxis": {
        "buckets": null,
        "format": "",
        "logBase": 0,
        "mode": "time",
        "name": null,
        "show": true,
        "values": []
      },
      "yaxes": [
        {
          "format": "s",
          "logBase": 2,
          "min": 0,
          "show": true
        },
        {
          "format": "short",
          "logBase": 1,
          "show": true
        }
      ],
      "yaxis": {
        "align": false,
        "alignLevel": null
      }
    },
    {
      "aliasColors": {},
      "bars": false,
      "dashLength": 10,
      "dashes": false,
      "datasource": "$datasource",
      "fill": 1,
      "gridPos": {
        "h": 7,
        "w": 12,
        "x": 12,
        "y": 41
      },
      "id": 34,
      "legend": {
        "avg": false,
        "current": false,
        "max": false,
        "min": false,
        "show": false,
        "total": false,
        "values": false
      },
      "lines": true,
      "linewidth": 1,
      "links": [],
      "nullPointMode": "null",
      "percentage": false,
      "pointradius": 5,
      "points": false,
      "renderer": "flot",
      "seriesOverrides": [
        {
          "alias": "/QPS.*/",
          "fill": 0,
          "linewidth": 2,
          "yaxis": 2
        }
      ],
      "spaceLength": 10,
      "stack": false,
      "steppedLine": false,
      "targets": [
        {
          "$$hashKey": "object:2470",
          "expr": "histogram_quantile(0.90, sum by(le, service) (rate(etl_worker_duration_seconds_bucket{service=~\"$service\", status=\"OK\"}[$interval])))",
          "format": "time_series",
          "interval": "60s",
          "intervalFactor": 1,
          "legendFormat": "99th",
          "refId": "B"
        },
        {
          "$$hashKey": "object:2471",
          "expr": "histogram_quantile(0.75, sum by(le, service) (rate(etl_worker_duration_seconds_bucket{service=~\"$service\", status=\"OK\"}[$interval])))",
          "format": "time_series",
          "hide": false,
          "interval": "60s",
          "intervalFactor": 1,
          "legendFormat": "75th",
          "refId": "A"
        },
        {
          "$$hashKey": "object:2472",
          "expr": "histogram_quantile(0.5, sum by(le, service) (rate(etl_worker_duration_seconds_bucket{service=~\"$service\", status=\"OK\"}[$interval])))",
          "format": "time_series",
          "interval": "60s",
          "intervalFactor": 1,
          "legendFormat": "50%",
          "refId": "C"
        },
        {
          "$$hashKey": "object:2473",
          "expr": "histogram_quantile(0.25, sum by(le, service) (rate(etl_worker_duration_seconds_bucket{service=~\"$service\", status=\"OK\"}[$interval])))",
          "format": "time_series",
          "hide": false,
          "interval": "60s",
          "intervalFactor": 1,
          "legendFormat": "25%",
          "refId": "D"
        },
        {
          "$$hashKey": "object:2474",
          "expr": "histogram_quantile(0.1, sum by(le, service) (rate(etl_worker_duration_seconds_bucket{service=~\"$service\", status=\"OK\"}[$interval])))",
          "format": "time_series",
          "hide": false,
          "interval": "60s",
          "intervalFactor": 1,
          "legendFormat": "10%",
          "refId": "E"
        }
      ],
      "thresholds": [],
      "timeFrom": null,
      "timeShift": null,
      "title": "Worker Duration Quantiles (Successful)",
      "tooltip": {
        "shared": true,
        "sort": 0,
        "value_type": "individual"
      },
      "type": "graph",
      "xaxis": {
        "buckets": null,
        "mode": "time",
        "name": null,
        "show": true,
        "values": []
      },
      "yaxes": [
        {
          "decimals": null,
          "format": "s",
          "label": null,
          "logBase": 1,
          "max": null,
          "min": "0",
          "show": true
        },
        {
          "format": "short",
          "label": null,
          "logBase": 1,
          "max": null,
          "min": null,
          "show": true
        }
      ],
      "yaxis": {
        "align": false,
        "alignLevel": null
      }
    },
    {
      "aliasColors": {},
      "bars": false,
      "dashLength": 10,
      "dashes": false,
      "datasource": "$datasource",
      "editable": false,
      "error": false,
      "fill": 1,
      "gridPos": {
        "h": 7,
        "w": 12,
        "x": 0,
        "y": 48
      },
      "id": 10,
      "isNew": false,
      "legend": {
        "alignAsTable": false,
        "avg": false,
        "current": false,
        "hideEmpty": false,
        "hideZero": false,
        "max": false,
        "min": false,
        "rightSide": false,
        "show": false,
        "total": false,
        "values": false
      },
      "lines": true,
      "linewidth": 1,
      "links": [],
      "nullPointMode": "null",
      "percentage": false,
      "pointradius": 5,
      "points": false,
      "renderer": "flot",
      "seriesOverrides": [
        {
          "alias": "/increase.*/",
          "yaxis": 2
        }
      ],
      "spaceLength": 10,
      "stack": false,
      "steppedLine": false,
      "targets": [
        {
          "$$hashKey": "object:2532",
          "expr": "sum by(version, service)(increase(etl_insertion_time_seconds_count{service=~\"$service\"}[$interval]))",
          "format": "time_series",
          "hide": false,
          "intervalFactor": 2,
          "legendFormat": "increase - {{version}} {{service}}",
          "refId": "A",
          "step": 120
        },
        {
          "$$hashKey": "object:2533",
          "expr": "sum by(version, service)(etl_insertion_time_seconds_count{service=~\"$service\"})",
          "format": "time_series",
          "hide": false,
          "intervalFactor": 2,
          "legendFormat": "total - {{version}} {{service}}",
          "refId": "B",
          "step": 120
        }
      ],
      "thresholds": [],
      "timeFrom": null,
      "timeShift": null,
      "title": "Total Insertion Calls [$interval]",
      "tooltip": {
        "shared": true,
        "sort": 0,
        "value_type": "individual"
      },
      "transparent": false,
      "type": "graph",
      "xaxis": {
        "buckets": null,
        "format": "",
        "logBase": 0,
        "mode": "time",
        "name": null,
        "show": true,
        "values": []
      },
      "yaxes": [
        {
          "format": "short",
          "label": "Total",
          "logBase": 1,
          "show": true
        },
        {
          "format": "short",
          "label": "Increases",
          "logBase": 1,
          "show": true
        }
      ],
      "yaxis": {
        "align": false,
        "alignLevel": null
      }
    },
    {
      "aliasColors": {},
      "bars": false,
      "dashLength": 10,
      "dashes": false,
      "datasource": "$datasource",
      "editable": false,
      "error": false,
      "fill": 0,
      "gridPos": {
        "h": 7,
        "w": 12,
        "x": 12,
        "y": 48
      },
      "id": 8,
      "isNew": false,
      "legend": {
        "alignAsTable": false,
        "avg": false,
        "current": false,
        "hideEmpty": true,
        "hideZero": true,
        "max": false,
        "min": false,
        "rightSide": false,
        "show": false,
        "total": false,
        "values": false
      },
      "lines": true,
      "linewidth": 1,
      "nullPointMode": "null",
      "percentage": false,
      "pointradius": 5,
      "points": false,
      "renderer": "flot",
      "seriesOverrides": [],
      "spaceLength": 10,
      "stack": false,
      "steppedLine": false,
      "targets": [
        {
          "$$hashKey": "object:2608",
          "expr": "etl_insertion_time_seconds_count{service=~\"$service\", status=\"succeed\"}",
          "format": "time_series",
          "interval": "60s",
          "intervalFactor": 1,
          "legendFormat": "ok: {{instance}}",
          "refId": "A",
          "step": 60
        },
        {
          "$$hashKey": "object:2609",
          "expr": "etl_insertion_time_seconds_count{service=~\"$service\", status=\"fail\"}",
          "format": "time_series",
          "interval": "60s",
          "intervalFactor": 1,
          "legendFormat": "fail: {{instance}}",
          "refId": "B",
          "step": 60
        }
      ],
      "thresholds": [],
      "timeFrom": null,
      "timeShift": null,
      "title": "Insertions per Instance",
      "tooltip": {
        "shared": true,
        "sort": 2,
        "value_type": "individual"
      },
      "transparent": false,
      "type": "graph",
      "xaxis": {
        "buckets": null,
        "format": "",
        "logBase": 0,
        "mode": "time",
        "name": null,
        "show": true,
        "values": []
      },
      "yaxes": [
        {
          "format": "short",
          "logBase": 1,
          "show": true
        },
        {
          "format": "short",
          "logBase": 1,
          "show": true
        }
      ],
      "yaxis": {
        "align": false,
        "alignLevel": null
      }
    },
    {
      "collapsed": false,
      "gridPos": {
        "h": 1,
        "w": 24,
        "x": 0,
        "y": 55
      },
      "id": 42,
      "panels": [],
      "repeat": null,
      "title": "Size Stats : $service",
      "type": "row"
    },
    {
      "aliasColors": {},
      "bars": false,
      "dashLength": 10,
      "dashes": false,
      "datasource": "$datasource",
      "editable": false,
      "error": false,
      "fill": 1,
      "gridPos": {
        "h": 7,
        "w": 12,
        "x": 0,
        "y": 56
      },
      "id": 35,
      "isNew": false,
      "legend": {
        "alignAsTable": false,
        "avg": false,
        "current": false,
        "hideEmpty": false,
        "hideZero": false,
        "max": false,
        "min": false,
        "rightSide": false,
        "show": false,
        "total": false,
        "values": false
      },
      "lines": true,
      "linewidth": 1,
      "links": [],
      "nullPointMode": "null",
      "percentage": false,
      "pointradius": 5,
      "points": false,
      "renderer": "flot",
      "seriesOverrides": [],
      "spaceLength": 10,
      "stack": false,
      "steppedLine": false,
      "targets": [
        {
          "$$hashKey": "object:2684",
          "expr": "histogram_quantile(0.99999, sum by(le, service)(rate(etl_test_file_size_bytes_bucket{service=~\"$service\", table=\"$table\"}[10m])))",
          "format": "time_series",
          "intervalFactor": 2,
          "legendFormat": "0.99999",
          "refId": "A",
          "step": 120
        },
        {
          "$$hashKey": "object:2685",
          "expr": " histogram_quantile(0.999, sum by(le, service)(rate(etl_test_file_size_bytes_bucket{service=~\"$service\", table=\"$table\"}[10m])))",
          "format": "time_series",
          "intervalFactor": 2,
          "legendFormat": ".999",
          "refId": "B",
          "step": 120
        },
        {
          "$$hashKey": "object:2686",
          "expr": " histogram_quantile(0.99, sum by(le, service)(rate(etl_test_file_size_bytes_bucket{service=~\"$service\", table=\"$table\"}[10m])))",
          "format": "time_series",
          "intervalFactor": 2,
          "legendFormat": ".99",
          "refId": "C",
          "step": 120
        },
        {
          "$$hashKey": "object:2687",
          "expr": " histogram_quantile(0.95, sum by(le, service)(rate(etl_test_file_size_bytes_bucket{service=~\"$service\", table=\"$table\"}[10m])))",
          "format": "time_series",
          "intervalFactor": 2,
          "legendFormat": ".95",
          "refId": "D",
          "step": 120
        },
        {
          "$$hashKey": "object:2688",
          "expr": " histogram_quantile(0.90, sum by(le, service)(rate(etl_test_file_size_bytes_bucket{service=~\"$service\", table=\"$table\"}[10m])))",
          "format": "time_series",
          "intervalFactor": 2,
          "legendFormat": ".90",
          "refId": "E",
          "step": 120
        },
        {
          "$$hashKey": "object:2689",
          "expr": " histogram_quantile(0.50, sum by(le, service)(rate(etl_test_file_size_bytes_bucket{service=~\"$service\", table=\"$table\"}[10m])))",
          "format": "time_series",
          "intervalFactor": 2,
          "legendFormat": ".50",
          "refId": "F",
          "step": 120
        },
        {
          "$$hashKey": "object:2690",
          "expr": " histogram_quantile(0.10, sum by(le, service)(rate(etl_test_file_size_bytes_bucket{service=~\"$service\", table=\"$table\"}[10m])))",
          "format": "time_series",
          "intervalFactor": 2,
          "legendFormat": ".10",
          "refId": "G",
          "step": 120
        }
      ],
      "thresholds": [],
      "timeFrom": null,
      "timeShift": null,
      "title": "File sizes",
      "tooltip": {
        "shared": true,
        "sort": 0,
        "value_type": "individual"
      },
      "transparent": false,
      "type": "graph",
      "xaxis": {
        "buckets": null,
        "format": "",
        "logBase": 0,
        "mode": "time",
        "name": null,
        "show": true,
        "values": []
      },
      "yaxes": [
        {
          "format": "short",
          "logBase": 1,
          "min": "0",
          "show": true
        },
        {
          "format": "short",
          "logBase": 1,
          "show": true
        }
      ],
      "yaxis": {
        "align": false,
        "alignLevel": null
      }
    },
    {
      "aliasColors": {},
      "bars": false,
      "dashLength": 10,
      "dashes": false,
      "datasource": "$datasource",
      "editable": false,
      "error": false,
      "fill": 1,
      "gridPos": {
        "h": 7,
        "w": 12,
        "x": 12,
        "y": 56
      },
      "id": 19,
      "isNew": false,
      "legend": {
        "alignAsTable": false,
        "avg": false,
        "current": false,
        "hideEmpty": false,
        "hideZero": false,
        "max": false,
        "min": false,
        "rightSide": false,
        "show": false,
        "total": false,
        "values": false
      },
      "lines": true,
      "linewidth": 1,
      "links": [],
      "nullPointMode": "null",
      "percentage": false,
      "pointradius": 5,
      "points": false,
      "renderer": "flot",
      "seriesOverrides": [],
      "spaceLength": 10,
      "stack": false,
      "steppedLine": false,
      "targets": [
        {
          "$$hashKey": "object:2758",
          "expr": "histogram_quantile(0.99999, sum by(le)(rate(etl_row_json_size_bucket{service=\"$service\", table=\"$table\"}[10m])))",
          "format": "time_series",
          "intervalFactor": 2,
          "legendFormat": "0.99999",
          "refId": "A",
          "step": 120
        },
        {
          "$$hashKey": "object:2759",
          "expr": " histogram_quantile(0.999, sum by(le)(rate(etl_row_json_size_bucket{service=\"$service\", table=\"$table\"}[10m])))",
          "format": "time_series",
          "intervalFactor": 2,
          "legendFormat": ".999",
          "refId": "B",
          "step": 120
        },
        {
          "$$hashKey": "object:2760",
          "expr": " histogram_quantile(0.99, sum by(le)(rate(etl_row_json_size_bucket{service=\"$service\", table=\"$table\"}[10m])))",
          "format": "time_series",
          "intervalFactor": 2,
          "legendFormat": ".99",
          "refId": "C",
          "step": 120
        },
        {
          "$$hashKey": "object:2761",
          "expr": " histogram_quantile(0.95, sum by(le)(rate(etl_row_json_size_bucket{service=\"$service\", table=\"$table\"}[10m])))",
          "format": "time_series",
          "intervalFactor": 2,
          "legendFormat": ".95",
          "refId": "D",
          "step": 120
        },
        {
          "$$hashKey": "object:2762",
          "expr": " histogram_quantile(0.90, sum by(le)(rate(etl_row_json_size_bucket{service=\"$service\", table=\"$table\"}[10m])))",
          "format": "time_series",
          "intervalFactor": 2,
          "legendFormat": ".90",
          "refId": "E",
          "step": 120
        },
        {
          "$$hashKey": "object:2763",
          "expr": " histogram_quantile(0.50, sum by(le)(rate(etl_row_json_size_bucket{service=\"$service\", table=\"$table\"}[10m])))",
          "format": "time_series",
          "intervalFactor": 2,
          "legendFormat": ".50",
          "refId": "F",
          "step": 120
        },
        {
          "$$hashKey": "object:2764",
          "expr": " histogram_quantile(0.10, sum by(le)(rate(etl_row_json_size_bucket{service=\"$service\", table=\"$table\"}[10m])))",
          "format": "time_series",
          "intervalFactor": 2,
          "legendFormat": ".10",
          "refId": "G",
          "step": 120
        }
      ],
      "thresholds": [],
      "timeFrom": null,
      "timeShift": null,
      "title": "Row sizes (json) : $service -> $table",
      "tooltip": {
        "shared": true,
        "sort": 0,
        "value_type": "individual"
      },
      "transparent": false,
      "type": "graph",
      "xaxis": {
        "buckets": null,
        "format": "",
        "logBase": 0,
        "mode": "time",
        "name": null,
        "show": true,
        "values": []
      },
      "yaxes": [
        {
          "format": "short",
          "logBase": 1,
          "min": "0",
          "show": true
        },
        {
          "format": "short",
          "logBase": 1,
          "show": true
        }
      ],
      "yaxis": {
        "align": false,
        "alignLevel": null
      }
    },
    {
      "aliasColors": {},
      "bars": false,
      "dashLength": 10,
      "dashes": false,
      "datasource": "$datasource",
      "editable": false,
      "error": false,
      "fill": 1,
      "gridPos": {
        "h": 7,
        "w": 12,
        "x": 0,
        "y": 63
      },
      "id": 22,
      "isNew": false,
      "legend": {
        "alignAsTable": false,
        "avg": false,
        "current": false,
        "hideEmpty": false,
        "hideZero": false,
        "max": false,
        "min": false,
        "rightSide": false,
        "show": false,
        "total": false,
        "values": false
      },
      "lines": true,
      "linewidth": 1,
      "links": [],
      "nullPointMode": "null",
      "percentage": false,
      "pointradius": 5,
      "points": false,
      "renderer": "flot",
      "seriesOverrides": [],
      "spaceLength": 10,
      "stack": false,
      "steppedLine": false,
      "targets": [
        {
          "$$hashKey": "object:2832",
          "expr": "histogram_quantile(0.99999, sum by(le)(rate(etl_entry_field_count_bucket{service=\"$service\", table=\"$table\"}[10m])))",
          "format": "time_series",
          "intervalFactor": 2,
          "legendFormat": "1.00",
          "refId": "A",
          "step": 120
        },
        {
          "$$hashKey": "object:2833",
          "expr": "histogram_quantile(0.99, sum by(le)(rate(etl_entry_field_count_bucket{service=\"$service\", table=\"$table\"}[10m])))",
          "format": "time_series",
          "intervalFactor": 2,
          "legendFormat": ".99",
          "refId": "B",
          "step": 120
        },
        {
          "$$hashKey": "object:2834",
          "expr": "histogram_quantile(.95, sum by(le)(rate(etl_entry_field_count_bucket{service=\"$service\", table=\"$table\"}[10m])))",
          "format": "time_series",
          "intervalFactor": 2,
          "legendFormat": ".95",
          "refId": "C",
          "step": 120
        },
        {
          "$$hashKey": "object:2835",
          "expr": "histogram_quantile(.90, sum by(le)(rate(etl_entry_field_count_bucket{service=\"$service\", table=\"$table\"}[10m])))",
          "format": "time_series",
          "intervalFactor": 2,
          "legendFormat": ".90",
          "refId": "D",
          "step": 120
        },
        {
          "$$hashKey": "object:2836",
          "expr": "histogram_quantile(0.50, sum by(le)(rate(etl_entry_field_count_bucket{service=\"$service\", table=\"$table\"}[10m])))",
          "format": "time_series",
          "intervalFactor": 2,
          "legendFormat": ".50",
          "refId": "E",
          "step": 120
        }
      ],
      "thresholds": [],
      "timeFrom": null,
      "timeShift": null,
      "title": "Rows per File -- Total Field Count",
      "tooltip": {
        "shared": true,
        "sort": 0,
        "value_type": "individual"
      },
      "transparent": false,
      "type": "graph",
      "xaxis": {
        "buckets": null,
        "format": "",
        "logBase": 0,
        "mode": "time",
        "name": null,
        "show": true,
        "values": []
      },
      "yaxes": [
        {
          "format": "short",
          "logBase": 1,
          "min": null,
          "show": true
        },
        {
          "format": "short",
          "logBase": 1,
          "show": true
        }
      ],
      "yaxis": {
        "align": false,
        "alignLevel": null
      }
    },
    {
      "aliasColors": {},
      "bars": false,
      "dashLength": 10,
      "dashes": false,
      "datasource": "$datasource",
      "editable": false,
      "error": false,
      "fill": 1,
      "gridPos": {
        "h": 7,
        "w": 12,
        "x": 12,
        "y": 63
      },
      "id": 24,
      "isNew": false,
      "legend": {
        "alignAsTable": false,
        "avg": false,
        "current": false,
        "hideEmpty": false,
        "hideZero": false,
        "max": false,
        "min": false,
        "rightSide": false,
        "show": false,
        "total": false,
        "values": false
      },
      "lines": true,
      "linewidth": 1,
      "links": [],
      "nullPointMode": "null",
      "percentage": false,
      "pointradius": 5,
      "points": false,
      "renderer": "flot",
      "seriesOverrides": [],
      "spaceLength": 10,
      "stack": false,
      "steppedLine": false,
      "targets": [
        {
          "$$hashKey": "object:2894",
          "expr": "histogram_quantile(.999, sum by(le)(rate(etl_delta_num_field_bucket{service=\"$service\"}[10m])))",
          "format": "time_series",
          "intervalFactor": 2,
          "legendFormat": "0.999",
          "refId": "A",
          "step": 120
        },
        {
          "$$hashKey": "object:2895",
          "expr": "histogram_quantile(0.95, sum by(le)(rate(etl_delta_num_field_bucket{service=\"$service\"}[10m])))",
          "format": "time_series",
          "intervalFactor": 2,
          "legendFormat": ".95",
          "refId": "B",
          "step": 120
        },
        {
          "$$hashKey": "object:2896",
          "expr": "histogram_quantile(0.90, sum by(le)(rate(etl_delta_num_field_bucket{service=\"$service\"}[10m])))",
          "format": "time_series",
          "intervalFactor": 2,
          "legendFormat": ".90",
          "refId": "C",
          "step": 120
        },
        {
          "$$hashKey": "object:2897",
          "expr": "histogram_quantile(0.80, sum by(le)(rate(etl_delta_num_field_bucket{service=\"$service\"}[10m])))",
          "format": "time_series",
          "intervalFactor": 2,
          "legendFormat": ".80",
          "refId": "D",
          "step": 120
        },
        {
          "$$hashKey": "object:2898",
          "expr": "histogram_quantile(0.50, sum by(le)(rate(etl_delta_num_field_bucket{service=\"$service\"}[10m])))",
          "format": "time_series",
          "intervalFactor": 2,
          "legendFormat": ".50",
          "refId": "E",
          "step": 120
        },
        {
          "$$hashKey": "object:2899",
          "expr": "histogram_quantile(0.20, sum by(le)(rate(etl_delta_num_field_bucket{service=\"$service\"}[10m])))",
          "format": "time_series",
          "intervalFactor": 2,
          "legendFormat": ".20",
          "refId": "F",
          "step": 120
        },
        {
          "$$hashKey": "object:2900",
          "expr": "histogram_quantile(0.10, sum by(le)(rate(etl_delta_num_field_bucket{service=\"$service\"}[10m])))",
          "format": "time_series",
          "intervalFactor": 2,
          "legendFormat": ".10",
          "refId": "G",
          "step": 120
        },
        {
          "$$hashKey": "object:2901",
          "expr": "histogram_quantile(0.010, sum by(le)(rate(etl_delta_num_field_bucket{service=\"$service\"}[10m])))",
          "format": "time_series",
          "intervalFactor": 2,
          "legendFormat": ".01",
          "refId": "H",
          "step": 120
        }
      ],
      "thresholds": [],
      "timeFrom": null,
      "timeShift": null,
      "title": "Fields per Row -- Snapshot Field Count",
      "tooltip": {
        "shared": true,
        "sort": 0,
        "value_type": "individual"
      },
      "transparent": false,
      "type": "graph",
      "xaxis": {
        "buckets": null,
        "format": "",
        "logBase": 0,
        "mode": "time",
        "name": null,
        "show": true,
        "values": []
      },
      "yaxes": [
        {
          "format": "short",
          "logBase": 1,
          "max": null,
          "min": null,
          "show": true
        },
        {
          "format": "short",
          "logBase": 1,
          "show": true
        }
      ],
      "yaxis": {
        "align": false,
        "alignLevel": null
      }
    }
  ],
  "refresh": false,
  "schemaVersion": 16,
  "style": "dark",
  "tags": [],
  "templating": {
    "list": [
      {
        "current": {
          "text": "Prometheus (mlab-oti)",
          "value": "Prometheus (mlab-oti)"
        },
        "hide": 0,
        "label": "Datasource",
        "name": "datasource",
        "options": [],
        "query": "prometheus",
        "refresh": 1,
        "regex": "Prometheus.*",
        "type": "datasource"
      },
      {
        "allFormat": "",
        "allValue": null,
        "current": {
          "text": "2m",
          "value": "2m"
        },
        "datasource": "$datasource",
        "hide": 0,
        "includeAll": false,
        "label": "",
        "multi": false,
        "multiFormat": "",
        "name": "interval",
        "options": [
          {
            "selected": false,
            "text": "10m",
            "value": "10m"
          },
          {
            "selected": false,
            "text": "1h",
            "value": "1h"
          },
          {
            "selected": false,
            "text": "3h",
            "value": "3h"
          },
          {
            "selected": false,
            "text": "6h",
            "value": "6h"
          },
          {
            "selected": false,
            "text": "12h",
            "value": "12h"
          },
          {
            "selected": false,
            "text": "18h",
            "value": "18h"
          },
          {
            "selected": false,
            "text": "1d",
            "value": "1d"
          },
          {
            "selected": false,
            "text": "2d",
            "value": "2d"
          },
          {
            "selected": false,
            "text": "1w",
            "value": "1w"
          },
          {
            "selected": false,
            "text": "4w",
            "value": "4w"
          },
          {
            "selected": false,
            "text": "13w",
            "value": "13w"
          },
          {
            "selected": false,
            "text": "1y",
            "value": "1y"
          }
        ],
        "query": "10m,1h,3h,6h,12h,18h,1d,2d,1w,4w,13w,1y",
        "refresh": false,
        "regex": "",
        "type": "custom"
      },
      {
        "allValue": null,
        "current": {
          "tags": [],
          "text": "ndt",
          "value": "ndt"
        },
        "datasource": "$datasource",
        "hide": 0,
        "includeAll": true,
        "label": "Table",
        "multi": false,
        "name": "table",
        "options": [],
        "query": "label_values(etl_worker_count, table)",
        "refresh": 1,
        "regex": "/(.+)/",
        "sort": 0,
        "tagValuesQuery": "",
        "tags": [],
        "tagsQuery": "",
        "type": "query",
        "useTags": false
      },
      {
        "allValue": null,
        "current": {
          "tags": [],
          "text": "etl-ndt-parser",
          "value": "etl-ndt-parser"
        },
        "datasource": "$datasource",
        "hide": 0,
        "includeAll": true,
        "label": "Service",
        "multi": false,
        "name": "service",
        "options": [],
        "query": "label_values(etl_worker_count, service)",
        "refresh": 1,
        "regex": "/.*-parser/",
        "sort": 1,
        "tagValuesQuery": "",
        "tags": [],
        "tagsQuery": "",
        "type": "query",
        "useTags": false
      },
      {
        "allValue": null,
        "current": {
          "tags": [],
          "text": "sum by(service)",
          "value": "sum by(service)"
        },
        "hide": 0,
        "includeAll": false,
        "label": "Show count",
        "multi": false,
        "name": "show_count",
        "options": [
          {
            "$$hashKey": "object:4183",
            "selected": false,
            "text": "absent",
            "value": "absent"
          },
          {
            "$$hashKey": "object:4184",
            "selected": true,
            "text": "sum by(service)",
            "value": "sum by(service)"
          }
        ],
        "query": "absent,sum by(service)",
        "type": "custom"
      }
    ]
  },
  "time": {
    "from": "now-3h",
    "to": "now"
  },
  "timepicker": {
    "refresh_intervals": [
      "5s",
      "10s",
      "30s",
      "1m",
      "5m",
      "15m",
      "30m",
      "1h",
      "2h",
      "1d"
    ],
    "time_options": [
      "5m",
      "15m",
      "1h",
      "6h",
      "12h",
      "24h",
      "2d",
      "7d",
      "30d"
    ]
  },
  "timezone": "utc",
  "title": "Pipeline: Parser",
  "uid": "000000037",
  "version": 10
}
