[
    {
        "labels": {
            "machine": "mlab4.lga0t.measurement-lab.org", 
            "experiment": "ndt.iupui", 
            "service": "ndt_e2e"
        }, 
        "targets": [
            "ndt.iupui.mlab4.lga0t.measurement-lab.org"
        ]
    }, 
    {
        "labels": {
            "machine": "mlab3.lga0t.measurement-lab.org", 
            "experiment": "ndt.iupui", 
            "service": "ndt_e2e"
        }, 
        "targets": [
            "ndt.iupui.mlab3.lga0t.measurement-lab.org"
        ]
    }, 
    {
        "labels": {
            "machine": "mlab2.lga0t.measurement-lab.org", 
            "experiment": "ndt.iupui", 
            "service": "ndt_e2e"
        }, 
        "targets": [
            "ndt.iupui.mlab2.lga0t.measurement-lab.org"
        ]
    }, 
    {
        "labels": {
            "machine": "mlab1.lga0t.measurement-lab.org", 
            "experiment": "ndt.iupui", 
            "service": "ndt_e2e"
        }, 
        "targets": [
            "ndt.iupui.mlab1.lga0t.measurement-lab.org"
        ]
    }, 
    {
        "labels": {
            "machine": "mlab4.lga1t.measurement-lab.org", 
            "experiment": "ndt.iupui", 
            "service": "ndt_e2e"
        }, 
        "targets": [
            "ndt.iupui.mlab4.lga1t.measurement-lab.org"
        ]
    }, 
    {
        "labels": {
            "machine": "mlab1.lga1t.measurement-lab.org", 
            "experiment": "ndt.iupui", 
            "service": "ndt_e2e"
        }, 
        "targets": [
            "ndt.iupui.mlab1.lga1t.measurement-lab.org"
        ]
    }, 
    {
        "labels": {
            "machine": "mlab2.lga1t.measurement-lab.org", 
            "experiment": "ndt.iupui", 
            "service": "ndt_e2e"
        }, 
        "targets": [
            "ndt.iupui.mlab2.lga1t.measurement-lab.org"
        ]
    }, 
    {
        "labels": {
            "machine": "mlab3.lga1t.measurement-lab.org", 
            "experiment": "ndt.iupui", 
            "service": "ndt_e2e"
        }, 
        "targets": [
            "ndt.iupui.mlab3.lga1t.measurement-lab.org"
        ]
    }, 
    {
        "labels": {
            "machine": "mlab2.iad0t.measurement-lab.org", 
            "experiment": "ndt.iupui", 
            "service": "ndt_e2e"
        }, 
        "targets": [
            "ndt.iupui.mlab2.iad0t.measurement-lab.org"
        ]
    }, 
    {
        "labels": {
            "machine": "mlab1.iad0t.measurement-lab.org", 
            "experiment": "ndt.iupui", 
            "service": "ndt_e2e"
        }, 
        "targets": [
            "ndt.iupui.mlab1.iad0t.measurement-lab.org"
        ]
    }, 
    {
        "labels": {
            "machine": "mlab4.iad0t.measurement-lab.org", 
            "experiment": "ndt.iupui", 
            "service": "ndt_e2e"
        }, 
        "targets": [
            "ndt.iupui.mlab4.iad0t.measurement-lab.org"
        ]
    }, 
    {
        "labels": {
            "machine": "mlab3.iad0t.measurement-lab.org", 
            "experiment": "ndt.iupui", 
            "service": "ndt_e2e"
        }, 
        "targets": [
            "ndt.iupui.mlab3.iad0t.measurement-lab.org"
        ]
    }, 
    {
        "labels": {
            "machine": "mlab2.iad1t.measurement-lab.org", 
            "experiment": "ndt.iupui", 
            "service": "ndt_e2e"
        }, 
        "targets": [
            "ndt.iupui.mlab2.iad1t.measurement-lab.org"
        ]
    }, 
    {
        "labels": {
            "machine": "mlab3.iad1t.measurement-lab.org", 
            "experiment": "ndt.iupui", 
            "service": "ndt_e2e"
        }, 
        "targets": [
            "ndt.iupui.mlab3.iad1t.measurement-lab.org"
        ]
    }, 
    {
        "labels": {
            "machine": "mlab4.iad1t.measurement-lab.org", 
            "experiment": "ndt.iupui", 
            "service": "ndt_e2e"
        }, 
        "targets": [
            "ndt.iupui.mlab4.iad1t.measurement-lab.org"
        ]
    }, 
    {
        "labels": {
            "machine": "mlab1.iad1t.measurement-lab.org", 
            "experiment": "ndt.iupui", 
            "service": "ndt_e2e"
        }, 
        "targets": [
            "ndt.iupui.mlab1.iad1t.measurement-lab.org"
        ]
    }
]